Workbook
Name Slicer_Item: #N/A
Name Slicer_Payment_Method: #N/A
Name Slicer_Transaction_Date: #N/A

Sheet Pivot_table
A3: Sum of Final_Total | D3: Sum of Final_Quantity | G3: Count of Transaction ID | I3: Distinct Count of Item | K3: Average of Price Per Unit
A4: 80491 | D4: 27243 | G4: 8996 | I4: 8 | K4: 2.9498666
A7: Row Labels | B7: Sum of Final_Total | D7: Row Labels | E7: Sum of Final_Total | G7: Row Labels | H7: Count of Final_Total | L7: =A4/G4 -> 8.9474211
A8: Cookie | B8: 3228 | D8: Cash | E8: 18513 | G8: January | H8: 740
A9: Tea | B9: 4938 | D9: Credit Card | E9: 18412.5 | G9: February | H9: 648
A10: Coffee | B10: 7068 | D10: Digital Wallet | E10: 18321 | G10: March | H10: 740
A11: Cake | B11: 10386 | D11: N/A | E11: 25244.5 | G11: April | H11: 696
A12: Juice | B12: 10515 | D12: Grand Total | E12: 80491 | G12: May | H12: 695
A13: Smoothie | B13: 13320 | G13: June | H13: 733
A14: Sandwich | B14: 13696 | G14: July | H14: 716
A15: Salad | B15: 17340 | G15: August | H15: 714
A16: Grand Total | B16: 80491 | G16: September | H16: 705
G17: October | H17: 765
G18: November | H18: 720
A19: Row Labels | B19: Sum of Final_Quantity | D19: Row Labels | E19: Sum of Final_Total | G19: December | H19: 708
A20: Cookie | B20: 3228 | D20: In-store | E20: 24677 | G20: Unknown | H20: 416
A21: Tea | B21: 3292 | D21: N/A | E21: 31958 | G21: Grand Total | H21: 8996
A22: Smoothie | B22: 3330 | D22: Takeaway | E22: 23856
A23: Sandwich | B23: 3424 | D23: Grand Total | E23: 80491
A24: Cake | B24: 3462 | G24: Row Labels | H24: Sum of Final_Quantity | I24: Sum of Final_Total
A25: Salad | B25: 3468 | G25: Cake | H25: 3462 | I25: 10386
A26: Juice | B26: 3505 | D26: Row Labels | E26: Sum of Final_Price | G26: Cookie | H26: 3228 | I26: 3228
A27: Coffee | B27: 3534 | D27: Sunday | E27: 3737 | G27: Juice | H27: 3505 | I27: 10515
A28: Grand Total | B28: 27243 | D28: Monday | E28: 3638 | G28: Salad | H28: 3468 | I28: 17340
D29: Tuesday | E29: 3501.5 | G29: Sandwich | H29: 3424 | I29: 13696
D30: Wednesday | E30: 3512 | G30: Smoothie | H30: 3330 | I30: 13320
D31: Thursday | E31: 3682.5 | G31: Tea | H31: 3292 | I31: 4938
D32: Friday | E32: 3685.5 | G32: Coffee | H32: 3534 | I32: 7068
D33: Saturday | E33: 3576 | G33: Grand Total | H33: 27243 | I33: 80491
D34: Unknown | E34: 1204.5
D35: Grand Total | E35: 26537

Sheet Dashboard

Sheet cleaned_data
A1: Transaction ID | B1: Item | C1: Quantity | D1: Final_Quantity | E1: Price Per Unit | F1: Final_Price | G1: Total Spent | H1: Final_Total | I1: Payment Method | J1: Location | K1: Transaction Date | L1: Month Name | M1: Day of Week | N1: Missing_Flag | O1: Quantity_Sourced
A2: TXN_1961373 | B2: Coffee | C2: 2 | D2: =IF(OR(C2="",C2="UNKNOWN",C2="ERROR"),IFERROR(VALUE(G2)/VALUE(E2),""),VALUE(C2)) -> 2 | E2: 2 | F2: =IF(OR(E2="",E2="UNKNOWN",E2="ERROR"),_xlfn.XLOOKUP(Table2[[#This Row],[Item]],Items_List!A:A,Items_List!B:B),E2) -> 2 | G2: 4 | H2: =D2*F2 -> 4 | I2: Credit Card | J2: Takeaway | K2: 45177 | L2: =IF(ISNUMBER(Table2[[#This Row],[Transaction Date]]),TEXT(Table2[[#This Row],[Transaction Date]],"mmmm"),"Unknown") -> September | M2: =IF(ISNUMBER(Table2[[#This Row],[Transaction Date]]),TEXT(Table2[[#This Row],[Transaction Date]],"dddd"),"Unknown") -> Friday | N2: =IF(OR(B2="",B2="unknown",B2="error",C2="",C2="unknown",C2="error",G2="",G2="error",G2="unknown"),1,0) -> 0 | O2: =IF(OR(C2="",C2="error",C2="unknown"),"Estimated","Actual") -> Actual
A3: TXN_4977031 | B3: Cake | C3: 4 | D3: =IF(OR(C3="",C3="UNKNOWN",C3="ERROR"),IFERROR(VALUE(G3)/VALUE(E3),""),VALUE(C3)) -> 4 | E3: 3 | F3: =IF(OR(E3="",E3="UNKNOWN",E3="ERROR"),_xlfn.XLOOKUP(Table2[[#This Row],[Item]],Items_List!A:A,Items_List!B:B),E3) -> 3 | G3: 12 | H3: =D3*F3 -> 12 | I3: Cash | J3: In-store | K3: 45062 | L3: =IF(ISNUMBER(Table2[[#This Row],[Transaction Date]]),TEXT(Table2[[#This Row],[Transaction Date]],"mmmm"),"Unknown") -> May | M3: =IF(ISNUMBER(Table2[[#This Row],[Transaction Date]]),TEXT(Table2[[#This Row],[Transaction Date]],"dddd"),"Unknown") -> Tuesday | N3: =IF(OR(B3="",B3="unknown",B3="error",C3="",C3="unknown",C3="error",G3="",G3="error",G3="unknown"),1,0) -> 0 | O3: =IF(OR(C3="",C3="error",C3="unknown"),"Estimated","Actual") -> Actual
A4: TXN_4271903 | B4: Cookie | C4: 4 | D4: =IF(OR(C4="",C4="UNKNOWN",C4="ERROR"),IFERROR(VALUE(G4)/VALUE(E4),""),VALUE(C4)) -> 4 | E4: 1 | F4: =IF(OR(E4="",E4="UNKNOWN",E4="ERROR"),_xlfn.XLOOKUP(Table2[[#This Row],[Item]],Items_List!A:A,Items_List!B:B),E4) -> 1 | G4: ERROR | H4: =D4*F4 -> 4 | I4: Credit Card | J4: In-store | K4: 45126 | L4: =IF(ISNUMBER(Table2[[#This Row],[Transaction Date]]),TEXT(Table2[[#This Row],[Transaction Date]],"mmmm"),"Unknown") -> July | M4: =IF(ISNUMBER(Table2[[#This Row],[Transaction Date]]),TEXT(Table2[[#This Row],[Transaction Date]],"dddd"),"Unknown") -> Wednesday | N4: =IF(OR(B4="",B4="unknown",B4="error",C4="",C4="unknown",C4="error",G4="",G4="error",G4="unknown"),1,0) -> 1 | O4: =IF(OR(C4="",C4="error",C4="unknown"),"Estimated","Actual") -> Actual
A5: TXN_7034554 | B5: Salad | C5: 2 | D5: =IF(OR(C5="",C5="UNKNOWN",C5="ERROR"),IFERROR(VALUE(G5)/VALUE(E5),""),VALUE(C5)) -> 2 | E5: 5 | F5: =IF(OR(E5="",E5="UNKNOWN",E5="ERROR"),_xlfn.XLOOKUP(Table2[[#This Row],[Item]],Items_List!A:A,Items_List!B:B),E5) -> 5 | G5: 10 | H5: =D5*F5 -> 10 | I5: N/A | J5: N/A | K5: 45043 | L5: =IF(ISNUMBER(Table2[[#This Row],[Transaction Date]]),TEXT(Table2[[#This Row],[Transaction Date]],"mmmm"),"Unknown") -> April | M5: =IF(ISNUMBER(Table2[[#This Row],[Transaction Date]]),TEXT(Table2[[#This Row],[Transaction Date]],"dddd"),"Unknown") -> Thursday | N5: =IF(OR(B5="",B5="unknown",B5="error",C5="",C5="unknown",C5="error",G5="",G5="error",G5="unknown"),1,0) -> 0 | O5: =IF(OR(C5="",C5="error",C5="unknown"),"Estimated","Actual") -> Actual
A6: TXN_3160411 | B6: Coffee | C6: 2 | D6: =IF(OR(C6="",C6="UNKNOWN",C6="ERROR"),IFERROR(VALUE(G6)/VALUE(E6),""),VALUE(C6)) -> 2 | E6: 2 | F6: =IF(OR(E6="",E6="UNKNOWN",E6="ERROR"),_xlfn.XLOOKUP(Table2[[#This Row],[Item]],Items_List!A:A,Items_List!B:B),E6) -> 2 | G6: 4 | H6: =D6*F6 -> 4 | I6: Digital Wallet | J6: In-store | K6: 45088 | L6: =IF(ISNUMBER(Table2[[#This Row],[Transaction Date]]),TEXT(Table2[[#This Row],[Transaction Date]],"mmmm"),"Unknown") -> June | M6: =IF(ISNUMBER(Table2[[#This Row],[Transaction Date]]),TEXT(Table2[[#This Row],[Transaction Date]],"dddd"),"Unknown") -> Sunday | N6: =IF(OR(B6="",B6="unknown",B6="error",C6="",C6="unknown",C6="error",G6="",G6="error",G6="unknown"),1,0) -> 0 | O6: =IF(OR(C6="",C6="error",C6="unknown"),"Estimated","Actual") -> Actual
A7: TXN_2602893 | B7: Smoothie | C7: 5 | D7: =IF(OR(C7="",C7="UNKNOWN",C7="ERROR"),IFERROR(VALUE(G7)/VALUE(E7),""),VALUE(C7)) -> 5 | E7: 4 | F7: =IF(OR(E7="",E7="UNKNOWN",E7="ERROR"),_xlfn.XLOOKUP(Table2[[#This Row],[Item]],Items_List!A:A,Items_List!B:B),E7) -> 4 | G7: 20 | H7: =D7*F7 -> 20 | I7: Credit Card | J7: N/A | K7: 45016 | L7: =IF(ISNUMBER(Table2[[#This Row],[Transaction Date]]),TEXT(Table2[[#This Row],[Transaction Date]],"mmmm"),"Unknown") -> March | M7: =IF(ISNUMBER(Table2[[#This Row],[Transaction Date]]),TEXT(Table2[[#This Row],[Transaction Date]],"dddd"),"Unknown") -> Friday | N7: =IF(OR(B7="",B7="unknown",B7="error",C7="",C7="unknown",C7="error",G7="",G7="error",G7="unknown"),1,0) -> 0 | O7: =IF(OR(C7="",C7="error",C7="unknown"),"Estimated","Actual") -> Actual | P7: 1
A8: TXN_6699534 | B8: Sandwich | C8: 4 | D8: =IF(OR(C8="",C8="UNKNOWN",C8="ERROR"),IFERROR(VALUE(G8)/VALUE(E8),""),VALUE(C8)) -> 4 | E8: 4 | F8: =IF(OR(E8="",E8="UNKNOWN",E8="ERROR"),_xlfn.XLOOKUP(Table2[[#This Row],[Item]],Items_List!A:A,Items_List!B:B),E8) -> 4 | G8: 16 | H8: =D8*F8 -> 16 | I8: Cash | J8: N/A | K8: 45227 | L8: =IF(ISNUMBER(Table2[[#This Row],[Transaction Date]]),TEXT(Table2[[#This Row],[Transaction Date]],"mmmm"),"Unknown") -> October | M8: =IF(ISNUMBER(Table2[[#This Row],[Transaction Date]]),TEXT(Table2[[#This Row],[Transaction Date]],"dddd"),"Unknown") -> Saturday | N8: =IF(OR(B8="",B8="unknown",B8="error",C8="",C8="unknown",C8="error",G8="",G8="error",G8="unknown"),1,0) -> 0 | O8: =IF(OR(C8="",C8="error",C8="unknown"),"Estimated","Actual") -> Actual
A9: TXN_2064365 | B9: Sandwich | C9: 5 | D9: =IF(OR(C9="",C9="UNKNOWN",C9="ERROR"),IFERROR(VALUE(G9)/VALUE(E9),""),VALUE(C9)) -> 5 | E9: 4 | F9: =IF(OR(E9="",E9="UNKNOWN",E9="ERROR"),_xlfn.XLOOKUP(Table2[[#This Row],[Item]],Items_List!A:A,Items_List!B:B),E9) -> 4 | G9: 20 | H9: =D9*F9 -> 20 | I9: N/A | J9: In-store | K9: 45291 | L9: =IF(ISNUMBER(Table2[[#This Row],[Transaction Date]]),TEXT(Table2[[#This Row],[Transaction Date]],"mmmm"),"Unknown") -> December | M9: =IF(ISNUMBER(Table2[[#This Row],[Transaction Date]]),TEXT(Table2[[#This Row],[Transaction Date]],"dddd"),"Unknown") -> Sunday | N9: =IF(OR(B9="",B9="unknown",B9="error",C9="",C9="unknown",C9="error",G9="",G9="error",G9="unknown"),1,0) -> 0 | O9: =IF(OR(C9="",C9="error",C9="unknown"),"Estimated","Actual") -> Actual
A10: TXN_2548360 | B10: Salad | C10: 5 | D10: =IF(OR(C10="",C10="UNKNOWN",C10="ERROR"),IFERROR(VALUE(G10)/VALUE(E10),""),VALUE(C10)) -> 5 | E10: 5 | F10: =IF(OR(E10="",E10="UNKNOWN",E10="ERROR"),_xlfn.XLOOKUP(Table2[[#This Row],[Item]],Items_List!A:A,Items_List!B:B),E10) -> 5 | G10: 25 | H10: =D10*F10 -> 25 | I10: Cash | J10: Takeaway | K10: 45237 | L10: =IF(ISNUMBER(Table2[[#This Row],[Transaction Date]]),TEXT(Table2[[#This Row],[Transaction Date]],"mmmm"),"Unknown") -> November | M10: =IF(ISNUMBER(Table2[[#This Row],[Transaction Date]]),TEXT(Table2[[#This Row],[Transaction Date]],"dddd"),"Unknown") -> Tuesday | N10: =IF(OR(B10="",B10="unknown",B10="error",C10="",C10="unknown",C10="error",G10="",G10="error",G10="unknown"),1,0) -> 0 | O10: =IF(OR(C10="",C10="error",C10="unknown"),"Estimated","Actual") -> Actual
A11: TXN_3051279 | B11: Sandwich | C11: 2 | D11: =IF(OR(C11="",C11="UNKNOWN",C11="ERROR"),IFERROR(VALUE(G11)/VALUE(E11),""),VALUE(C11)) -> 2 | E11: 4 | F11: =IF(OR(E11="",E11="UNKNOWN",E11="ERROR"),_xlfn.XLOOKUP(Table2[[#This Row],[Item]],Items_List!A:A,Items_List!B:B),E11) -> 4 | G11: 8 | H11: =D11*F11 -> 8 | I11: Credit Card | J11: Takeaway | L11: =IF(ISNUMBER(Table2[[#This Row],[Transaction Date]]),TEXT(Table2[[#This Row],[Transaction Date]],"mmmm"),"Unknown") -> Unknown | M11: =IF(ISNUMBER(Table2[[#This Row],[Transaction Date]]),TEXT(Table2[[#This Row],[Transaction Date]],"dddd"),"Unknown") -> Unknown | N11: =IF(OR(B11="",B11="unknown",B11="error",C11="",C11="unknown",C11="error",G11="",G11="error",G11="unknown"),1,0) -> 0 | O11: =IF(OR(C11="",C11="error",C11="unknown"),"Estimated","Actual") -> Actual
A12: TXN_7619095 | B12: Sandwich | C12: 2 | D12: =IF(OR(C12="",C12="UNKNOWN",C12="ERROR"),IFERROR(VALUE(G12)/VALUE(E12),""),VALUE(C12)) -> 2 | E12: 4 | F12: =IF(OR(E12="",E12="UNKNOWN",E12="ERROR"),_xlfn.XLOOKUP(Table2[[#This Row],[Item]],Items_List!A:A,Items_List!B:B),E12) -> 4 | G12: 8 | H12: =D12*F12 -> 8 | I12: Cash | J12: In-store | K12: 45049 | L12: =IF(ISNUMBER(Table2[[#This Row],[Transaction Date]]),TEXT(Table2[[#This Row],[Transaction Date]],"mmmm"),"Unknown") -> May | M12: =IF(ISNUMBER(Table2[[#This Row],[Transaction Date]]),TEXT(Table2[[#This Row],[Transaction Date]],"dddd"),"Unknown") -> Wednesday | N12: =IF(OR(B12="",B12="unknown",B12="error",C12="",C12="unknown",C12="error",G12="",G12="error",G12="unknown"),1,0) -> 0 | O12: =IF(OR(C12="",C12="error",C12="unknown"),"Estimated","Actual") -> Actual
A13: TXN_9437049 | B13: Cookie | C13: 5 | D13: =IF(OR(C13="",C13="UNKNOWN",C13="ERROR"),IFERROR(VALUE(G13)/VALUE(E13),""),VALUE(C13)) -> 5 | E13: 1 | F13: =IF(OR(E13="",E13="UNKNOWN",E13="ERROR"),_xlfn.XLOOKUP(Table2[[#This Row],[Item]],Items_List!A:A,Items_List!B:B),E13) -> 1 | G13: 5 | H13: =D13*F13 -> 5 | I13: N/A | J13: Takeaway | K13: 45078 | L13: =IF(ISNUMBER(Table2[[#This Row],[Transaction Date]]),TEXT(Table2[[#This Row],[Transaction Date]],"mmmm"),"Unknown") -> June | M13: =IF(ISNUMBER(Table2[[#This Row],[Transaction Date]]),TEXT(Table2[[#This Row],[Transaction Date]],"dddd"),"Unknown") -> Thursday | N13: =IF(OR(B13="",B13="unknown",B13="error",C13="",C13="unknown",C13="error",G13="",G13="error",G13="unknown"),1,0) -> 0 | O13: =IF(OR(C13="",C13="error",C13="unknown"),"Estimated","Actual") -> Actual
A14: TXN_2847255 | B14: Salad | C14: 3 | D14: =IF(OR(C14="",C14="UNKNOWN",C14="ERROR"),IFERROR(VALUE(G14)/VALUE(E14),""),VALUE(C14)) -> 3 | E14: 5 | F14: =IF(OR(E14="",E14="UNKNOWN",E14="ERROR"),_xlfn.XLOOKUP(Table2[[#This Row],[Item]],Items_List!A:A,Items_List!B:B),E14) -> 5 | G14: 15 | H14: =D14*F14 -> 15 | I14: Credit Card | J14: In-store | K14: 45245 | L14: =IF(ISNUMBER(Table2[[#This Row],[Transaction Date]]),TEXT(Table2[[#This Row],[Transaction Date]],"mmmm"),"Unknown") -> November | M14: =IF(ISNUMBER(Table2[[#This Row],[Transaction Date]]),TEXT(Table2[[#This Row],[Transaction Date]],"dddd"),"Unknown") -> Wednesday | N14: =IF(OR(B14="",B14="unknown",B14="error",C14="",C14="unknown",C14="error",G14="",G14="error",G14="unknown"),1,0) -> 0 | O14: =IF(OR(C14="",C14="error",C14="unknown"),"Estimated","Actual") -> Actual
A15: TXN_3765707 | B15: Sandwich | C15: 1 | D15: =IF(OR(C15="",C15="UNKNOWN",C15="ERROR"),IFERROR(VALUE(G15)/VALUE(E15),""),VALUE(C15)) -> 1 | E15: 4 | F15: =IF(OR(E15="",E15="UNKNOWN",E15="ERROR"),_xlfn.XLOOKUP(Table2[[#This Row],[Item]],Items_List!A:A,Items_List!B:B),E15) -> 4 | G15: 4 | H15: =D15*F15 -> 4 | I15: N/A | J15: N/A | K15: 45087 | L15: =IF(ISNUMBER(Table2[[#This Row],[Transaction Date]]),TEXT(Table2[[#This Row],[Transaction Date]],"mmmm"),"Unknown") -> June | M15: =IF(ISNUMBER(Table2[[#This Row],[Transaction Date]]),TEXT(Table2[[#This Row],[Transaction Date]],"dddd"),"Unknown") -> Saturday | N15: =IF(OR(B15="",B15="unknown",B15="error",C15="",C15="unknown",C15="error",G15="",G15="error",G15="unknown"),1,0) -> 0 | O15: =IF(OR(C15="",C15="error",C15="unknown"),"Estimated","Actual") -> Actual
A16: TXN_6769710 | B16: Juice | C16: 2 | D16: =IF(OR(C16="",C16="UNKNOWN",C16="ERROR"),IFERROR(VALUE(G16)/VALUE(E16),""),VALUE(C16)) -> 2 | E16: 3 | F16: =IF(OR(E16="",E16="UNKNOWN",E16="ERROR"),_xlfn.XLOOKUP(Table2[[#This Row],[Item]],Items_List!A:A,Items_List!B:B),E16) -> 3 | G16: 6 | H16: =D16*F16 -> 6 | I16: Cash | J16: In-store | K16: 44981 | L16: =IF(ISNUMBER(Table2[[#This Row],[Transaction Date]]),TEXT(Table2[[#This Row],[Transaction Date]],"mmmm"),"Unknown") -> February | M16: =IF(ISNUMBER(Table2[[#This Row],[Transaction Date]]),TEXT(Table2[[#This Row],[Transaction Date]],"dddd"),"Unknown") -> Friday | N16: =IF(OR(B16="",B16="unknown",B16="error",C16="",C16="unknown",C16="error",G16="",G16="error",G16="unknown"),1,0) -> 0 | O16: =IF(OR(C16="",C16="error",C16="unknown"),"Estimated","Actual") -> Actual
A17: TXN_8876618 | B17: Cake | C17: 5 | D17: =IF(OR(C17="",C17="UNKNOWN",C17="ERROR"),IFERROR(VALUE(G17)/VALUE(E17),""),VALUE(C17)) -> 5 | E17: 3 | F17: =IF(OR(E17="",E17="UNKNOWN",E17="ERROR"),_xlfn.XLOOKUP(Table2[[#This Row],[Item]],Items_List!A:A,Items_List!B:B),E17) -> 3 | G17: 15 | H17: =D17*F17 -> 15 | I17: Cash | J17: N/A | K17: 45010 | L17: =IF(ISNUMBER(Table2[[#This Row],[Transaction Date]]),TEXT(Table2[[#This Row],[Transaction Date]],"mmmm"),"Unknown") -> March | M17: =IF(ISNUMBER(Table2[[#This Row],[Transaction Date]]),TEXT(Table2[[#This Row],[Transaction Date]],"dddd"),"Unknown") -> Saturday | N17: =IF(OR(B17="",B17="unknown",B17="error",C17="",C17="unknown",C17="error",G17="",G17="error",G17="unknown"),1,0) -> 0 | O17: =IF(OR(C17="",C17="error",C17="unknown"),"Estimated","Actual") -> Actual
A18: TXN_3709394 | B18: Juice | C18: 4 | D18: =IF(OR(C18="",C18="UNKNOWN",C18="ERROR"),IFERROR(VALUE(G18)/VALUE(E18),""),VALUE(C18)) -> 4 | E18: 3 | F18: =IF(OR(E18="",E18="UNKNOWN",E18="ERROR"),_xlfn.XLOOKUP(Table2[[#This Row],[Item]],Items_List!A:A,Items_List!B:B),E18) -> 3 | G18: 12 | H18: =D18*F18 -> 12 | I18: Cash | J18: Takeaway | K18: 44941 | L18: =IF(ISNUMBER(Table2[[#This Row],[Transaction Date]]),TEXT(Table2[[#This Row],[Transaction Date]],"mmmm"),"Unknown") -> January | M18: =IF(ISNUMBER(Table2[[#This Row],[Transaction Date]]),TEXT(Table2[[#This Row],[Transaction Date]],"dddd"),"Unknown") -> Sunday | N18: =IF(OR(B18="",B18="unknown",B18="error",C18="",C18="unknown",C18="error",G18="",G18="error",G18="unknown"),1,0) -> 0 | O18: =IF(OR(C18="",C18="error",C18="unknown"),"Estimated","Actual") -> Actual
A19: TXN_3522028 | B19: Smoothie | C19: ERROR | D19: =IF(OR(C19="",C19="UNKNOWN",C19="ERROR"),IFERROR(VALUE(G19)/VALUE(E19),""),VALUE(C19)) -> 5 | E19: 4 | F19: =IF(OR(E19="",E19="UNKNOWN",E19="ERROR"),_xlfn.XLOOKUP(Table2[[#This Row],[Item]],Items_List!A:A,Items_List!B:B),E19) -> 4 | G19: 20 | H19: =D19*F19 -> 20 | I19: Cash | J19: In-store | K19: 45020 | L19: =IF(ISNUMBER(Table2[[#This Row],[Transaction Date]]),TEXT(Table2[[#This Row],[Transaction Date]],"mmmm"),"Unknown") -> April | M19: =IF(ISNUMBER(Table2[[#This Row],[Transaction Date]]),TEXT(Table2[[#This Row],[Transaction Date]],"dddd"),"Unknown") -> Tuesday | N19: =IF(OR(B19="",B19="unknown",B19="error",C19="",C19="unknown",C19="error",G19="",G19="error",G19="unknown"),1,0) -> 1 | O19: =IF(OR(C19="",C19="error",C19="unknown"),"Estimated","Actual") -> Estimated
A20: TXN_3567645 | B20: Smoothie | C20: 4 | D20: =IF(OR(C20="",C20="UNKNOWN",C20="ERROR"),IFERROR(VALUE(G20)/VALUE(E20),""),VALUE(C20)) -> 4 | E20: 4 | F20: =IF(OR(E20="",E20="UNKNOWN",E20="ERROR"),_xlfn.XLOOKUP(Table2[[#This Row],[Item]],Items_List!A:A,Items_List!B:B),E20) -> 4 | G20: 16 | H20: =D20*F20 -> 16 | I20: Credit Card | J20: Takeaway | K20: 45015 | L20: =IF(ISNUMBER(Table2[[#This Row],[Transaction Date]]),TEXT(Table2[[#This Row],[Transaction Date]],"mmmm"),"Unknown") -> March | M20: =IF(ISNUMBER(Table2[[#This Row],[Transaction Date]]),TEXT(Table2[[#This Row],[Transaction Date]],"dddd"),"Unknown") -> Thursday | N20: =IF(OR(B20="",B20="unknown",B20="error",C20="",C20="unknown",C20="error",G20="",G20="error",G20="unknown"),1,0) -> 0 | O20: =IF(OR(C20="",C20="error",C20="unknown"),"Estimated","Actual") -> Actual
A21: TXN_5132361 | B21: Sandwich | C21: 3 | D21: =IF(OR(C21="",C21="UNKNOWN",C21="ERROR"),IFERROR(VALUE(G21)/VALUE(E21),""),VALUE(C21)) -> 3 | E21: 4 | F21: =IF(OR(E21="",E21="UNKNOWN",E21="ERROR"),_xlfn.XLOOKUP(Table2[[#This Row],[Item]],Items_List!A:A,Items_List!B:B),E21) -> 4 | G21: 12 | H21: =D21*F21 -> 12 | I21: Digital Wallet | J21: Takeaway | K21: 45261 | L21: =IF(ISNUMBER(Table2[[#This Row],[Transaction Date]]),TEXT(Table2[[#This Row],[Transaction Date]],"mmmm"),"Unknown") -> December | M21: =IF(ISNUMBER(Table2[[#This Row],[Transaction Date]]),TEXT(Table2[[#This Row],[Transaction Date]],"dddd"),"Unknown") -> Friday | N21: =IF(OR(B21="",B21="unknown",B21="error",C21="",C21="unknown",C21="error",G21="",G21="error",G21="unknown"),1,0) -> 0 | O21: =IF(OR(C21="",C21="error",C21="unknown"),"Estimated","Actual") -> Actual
A22: TXN_2616390 | B22: Sandwich | C22: 2 | D22: =IF(OR(C22="",C22="UNKNOWN",C22="ERROR"),IFERROR(VALUE(G22)/VALUE(E22),""),VALUE(C22)) -> 2 | E22: 4 | F22: =IF(OR(E22="",E22="UNKNOWN",E22="ERROR"),_xlfn.XLOOKUP(Table2[[#This Row],[Item]],Items_List!A:A,Items_List!B:B),E22) -> 4 | G22: 8 | H22: =D22*F22 -> 8 | I22: N/A | J22: N/A | K22: 45187 | L22: =IF(ISNUMBER(Table2[[#This Row],[Transaction Date]]),TEXT(Table2[[#This Row],[Transaction Date]],"mmmm"),"Unknown") -> September | M22: =IF(ISNUMBER(Table2[[#This Row],[Transaction Date]]),TEXT(Table2[[#This Row],[Transaction Date]],"dddd"),"Unknown") -> Monday | N22: =IF(OR(B22="",B22="unknown",B22="error",C22="",C22="unknown",C22="error",G22="",G22="error",G22="unknown"),1,0) -> 0 | O22: =IF(OR(C22="",C22="error",C22="unknown"),"Estimated","Actual") -> Actual
A23: TXN_9400181 | B23: Sandwich | C23: 5 | D23: =IF(OR(C23="",C23="UNKNOWN",C23="ERROR"),IFERROR(VALUE(G23)/VALUE(E23),""),VALUE(C23)) -> 5 | E23: 4 | F23: =IF(OR(E23="",E23="UNKNOWN",E23="ERROR"),_xlfn.XLOOKUP(Table2[[#This Row],[Item]],Items_List!A:A,Items_List!B:B),E23) -> 4 | G23: 20 | H23: =D23*F23 -> 20 | I23: Cash | J23: In-store | K23: 45080 | L23: =IF(ISNUMBER(Table2[[#This Row],[Transaction Date]]),TEXT(Table2[[#This Row],[Transaction Date]],"mmmm"),"Unknown") -> June | M23: =IF(ISNUMBER(Table2[[#This Row],[Transaction Date]]),TEXT(Table2[[#This Row],[Transaction Date]],"dddd"),"Unknown") -> Saturday | N23: =IF(OR(B23="",B23="unknown",B23="error",C23="",C23="unknown",C23="error",G23="",G23="error",G23="unknown"),1,0) -> 0 | O23: =IF(OR(C23="",C23="error",C23="unknown"),"Estimated","Actual") -> Actual
A24: TXN_7958992 | B24: Smoothie | C24: 3 | D24: =IF(OR(C24="",C24="UNKNOWN",C24="ERROR"),IFERROR(VALUE(G24)/VALUE(E24),""),VALUE(C24)) -> 3 | E24: 4 | F24: =IF(OR(E24="",E24="UNKNOWN",E24="ERROR"),_xlfn.XLOOKUP(Table2[[#This Row],[Item]],Items_List!A:A,Items_List!B:B),E24) -> 4 | H24: =D24*F24 -> 12 | I24: N/A | J24: N/A | K24: 45273 | L24: =IF(ISNUMBER(Table2[[#This Row],[Transaction Date]]),TEXT(Table2[[#This Row],[Transaction Date]],"mmmm"),"Unknown") -> December | M24: =IF(ISNUMBER(Table2[[#This Row],[Transaction Date]]),TEXT(Table2[[#This Row],[Transaction Date]],"dddd"),"Unknown") -> Wednesday | N24: =IF(OR(B24="",B24="unknown",B24="error",C24="",C24="unknown",C24="error",G24="",G24="error",G24="unknown"),1,0) -> 1 | O24: =IF(OR(C24="",C24="error",C24="unknown"),"Estimated","Actual") -> Actual
A25: TXN_5183041 | B25: Cookie | C25: 5 | D25: =IF(OR(C25="",C25="UNKNOWN",C25="ERROR"),IFERROR(VALUE(G25)/VALUE(E25),""),VALUE(C25)) -> 5 | E25: 1 | F25: =IF(OR(E25="",E25="UNKNOWN",E25="ERROR"),_xlfn.XLOOKUP(Table2[[#This Row],[Item]],Items_List!A:A,Items_List!B:B),E25) -> 1 | G25: 5 | H25: =D25*F25 -> 5 | I25: Credit Card | J25: In-store | K25: 45036 | L25: =IF(ISNUMBER(Table2[[#This Row],[Transaction Date]]),TEXT(Table2[[#This Row],[Transaction Date]],"mmmm"),"Unknown") -> April | M25: =IF(ISNUMBER(Table2[[#This Row],[Transaction Date]]),TEXT(Table2[[#This Row],[Transaction Date]],"dddd"),"Unknown") -> Thursday | N25: =IF(OR(B25="",B25="unknown",B25="error",C25="",C25="unknown",C25="error",G25="",G25="error",G25="unknown"),1,0) -> 0 | O25: =IF(OR(C25="",C25="error",C25="unknown"),"Estimated","Actual") -> Actual
A26: TXN_5695074 | B26: Juice | C26: 4 | D26: =IF(OR(C26="",C26="UNKNOWN",C26="ERROR"),IFERROR(VALUE(G26)/VALUE(E26),""),VALUE(C26)) -> 4 | E26: 3 | F26: =IF(OR(E26="",E26="UNKNOWN",E26="ERROR"),_xlfn.XLOOKUP(Table2[[#This Row],[Item]],Items_List!A:A,Items_List!B:B),E26) -> 3 | G26: 12 | H26: =D26*F26 -> 12 | I26: Credit Card | J26: Takeaway | K26: 45026 | L26: =IF(ISNUMBER(Table2[[#This Row],[Transaction Date]]),TEXT(Table2[[#This Row],[Transaction Date]],"mmmm"),"Unknown") -> April | M26: =IF(ISNUMBER(Table2[[#This Row],[Transaction Date]]),TEXT(Table2[[#This Row],[Transaction Date]],"dddd"),"Unknown") -> Monday | N26: =IF(OR(B26="",B26="unknown",B26="error",C26="",C26="unknown",C26="error",G26="",G26="error",G26="unknown"),1,0) -> 0 | O26: =IF(OR(C26="",C26="error",C26="unknown"),"Estimated","Actual") -> Actual
A27: TXN_8467949 | B27: Smoothie | C27: 5 | D27: =IF(OR(C27="",C27="UNKNOWN",C27="ERROR"),IFERROR(VALUE(G27)/VALUE(E27),""),VALUE(C27)) -> 5 | E27: 4 | F27: =IF(OR(E27="",E27="UNKNOWN",E27="ERROR"),_xlfn.XLOOKUP(Table2[[#This Row],[Item]],Items_List!A:A,Items_List!B:B),E27) -> 4 | G27: 20 | H27: =D27*F27 -> 20 | I27: Credit Card | J27: N/A | K27: 44996 | L27: =IF(ISNUMBER(Table2[[#This Row],[Transaction Date]]),TEXT(Table2[[#This Row],[Transaction Date]],"mmmm"),"Unknown") -> March | M27: =IF(ISNUMBER(Table2[[#This Row],[Transaction Date]]),TEXT(Table2[[#This Row],[Transaction Date]],"dddd"),"Unknown") -> Saturday | N27: =IF(OR(B27="",B27="unknown",B27="error",C27="",C27="unknown",C27="error",G27="",G27="error",G27="unknown"),1,0) -> 0 | O27: =IF(OR(C27="",C27="error",C27="unknown"),"Estimated","Actual") -> Actual
A28: TXN_7640952 | B28: Cake | C28: 4 | D28: =IF(OR(C28="",C28="UNKNOWN",C28="ERROR"),IFERROR(VALUE(G28)/VALUE(E28),""),VALUE(C28)) -> 4 | E28: 3 | F28: =IF(OR(E28="",E28="UNKNOWN",E28="ERROR"),_xlfn.XLOOKUP(Table2[[#This Row],[Item]],Items_List!A:A,Items_List!B:B),E28) -> 3 | G28: 12 | H28: =D28*F28 -> 12 | I28: Digital Wallet | J28: Takeaway | L28: =IF(ISNUMBER(Table2[[#This Row],[Transaction Date]]),TEXT(Table2[[#This Row],[Transaction Date]],"mmmm"),"Unknown") -> Unknown | M28: =IF(ISNUMBER(Table2[[#This Row],[Transaction Date]]),TEXT(Table2[[#This Row],[Transaction Date]],"dddd"),"Unknown") -> Unknown | N28: =IF(OR(B28="",B28="unknown",B28="error",C28="",C28="unknown",C28="error",G28="",G28="error",G28="unknown"),1,0) -> 0 | O28: =IF(OR(C28="",C28="error",C28="unknown"),"Estimated","Actual") -> Actual
A29: TXN_9677376 | B29: Smoothie | C29: 4 | D29: =IF(OR(C29="",C29="UNKNOWN",C29="ERROR"),IFERROR(VALUE(G29)/VALUE(E29),""),VALUE(C29)) -> 4 | E29: 4 | F29: =IF(OR(E29="",E29="UNKNOWN",E29="ERROR"),_xlfn.XLOOKUP(Table2[[#This Row],[Item]],Items_List!A:A,Items_List!B:B),E29) -> 4 | G29: 16 | H29: =D29*F29 -> 16 | I29: N/A | J29: In-store | K29: 45153 | L29: =IF(ISNUMBER(Table2[[#This Row],[Transaction Date]]),TEXT(Table2[[#This Row],[Transaction Date]],"mmmm"),"Unknown") -> August | M29: =IF(ISNUMBER(Table2[[#This Row],[Transaction Date]]),TEXT(Table2[[#This Row],[Transaction Date]],"dddd"),"Unknown") -> Tuesday | N29: =IF(OR(B29="",B29="unknown",B29="error",C29="",C29="unknown",C29="error",G29="",G29="error",G29="unknown"),1,0) -> 0 | O29: =IF(OR(C29="",C29="error",C29="unknown"),"Estimated","Actual") -> Actual
A30: TXN_8853997 | B30: Smoothie | C30: 2 | D30: =IF(OR(C30="",C30="UNKNOWN",C30="ERROR"),IFERROR(VALUE(G30)/VALUE(E30),""),VALUE(C30)) -> 2 | E30: 4 | F30: =IF(OR(E30="",E30="UNKNOWN",E30="ERROR"),_xlfn.XLOOKUP(Table2[[#This Row],[Item]],Items_List!A:A,Items_List!B:B),E30) -> 4 | G30: 8 | H30: =D30*F30 -> 8 | I30: Digital Wallet | J30: Takeaway | K30: 45208 | L30: =IF(ISNUMBER(Table2[[#This Row],[Transaction Date]]),TEXT(Table2[[#This Row],[Transaction Date]],"mmmm"),"Unknown") -> October | M30: =IF(ISNUMBER(Table2[[#This Row],[Transaction Date]]),TEXT(Table2[[#This Row],[Transaction Date]],"dddd"),"Unknown") -> Monday | N30: =IF(OR(B30="",B30="unknown",B30="error",C30="",C30="unknown",C30="error",G30="",G30="error",G30="unknown"),1,0) -> 0 | O30: =IF(OR(C30="",C30="error",C30="unknown"),"Estimated","Actual") -> Actual
A31: TXN_9130559 | B31: Sandwich | C31: 1 | D31: =IF(OR(C31="",C31="UNKNOWN",C31="ERROR"),IFERROR(VALUE(G31)/VALUE(E31),""),VALUE(C31)) -> 1 | E31: 4 | F31: =IF(OR(E31="",E31="UNKNOWN",E31="ERROR"),_xlfn.XLOOKUP(Table2[[#This Row],[Item]],Items_List!A:A,Items_List!B:B),E31) -> 4 | G31: 4 | H31: =D31*F31 -> 4 | I31: Credit Card | J31: N/A | K31: 45074 | L31: =IF(ISNUMBER(Table2[[#This Row],[Transaction Date]]),TEXT(Table2[[#This Row],[Transaction Date]],"mmmm"),"Unknown") -> May | M31: =IF(ISNUMBER(Table2[[#This Row],[Transaction Date]]),TEXT(Table2[[#This Row],[Transaction Date]],"dddd"),"Unknown") -> Sunday | N31: =IF(OR(B31="",B31="unknown",B31="error",C31="",C31="unknown",C31="error",G31="",G31="error",G31="unknown"),1,0) -> 0 | O31: =IF(OR(C31="",C31="error",C31="unknown"),"Estimated","Actual") -> Actual
A32: TXN_1080432 | B32: Salad | C32: 2 | D32: =IF(OR(C32="",C32="UNKNOWN",C32="ERROR"),IFERROR(VALUE(G32)/VALUE(E32),""),VALUE(C32)) -> 2 | E32: 5 | F32: =IF(OR(E32="",E32="UNKNOWN",E32="ERROR"),_xlfn.XLOOKUP(Table2[[#This Row],[Item]],Items_List!A:A,Items_List!B:B),E32) -> 5 | G32: 10 | H32: =D32*F32 -> 10 | I32: Credit Card | J32: In-store | K32: 45045 | L32: =IF(ISNUMBER(Table2[[#This Row],[Transaction Date]]),TEXT(Table2[[#This Row],[Transaction Date]],"mmmm"),"Unknown") -> April | M32: =IF(ISNUMBER(Table2[[#This Row],[Transaction Date]]),TEXT(Table2[[#This Row],[Transaction Date]],"dddd"),"Unknown") -> Saturday | N32: =IF(OR(B32="",B32="unknown",B32="error",C32="",C32="unknown",C32="error",G32="",G32="error",G32="unknown"),1,0) -> 0 | O32: =IF(OR(C32="",C32="error",C32="unknown"),"Estimated","Actual") -> Actual
A33: TXN_2655815 | B33: Smoothie | C33: 4 | D33: =IF(OR(C33="",C33="UNKNOWN",C33="ERROR"),IFERROR(VALUE(G33)/VALUE(E33),""),VALUE(C33)) -> 4 | E33: 4 | F33: =IF(OR(E33="",E33="UNKNOWN",E33="ERROR"),_xlfn.XLOOKUP(Table2[[#This Row],[Item]],Items_List!A:A,Items_List!B:B),E33) -> 4 | G33: 16 | H33: =D33*F33 -> 16 | I33: N/A | J33: Takeaway | K33: 45085 | L33: =IF(ISNUMBER(Table2[[#This Row],[Transaction Date]]),TEXT(Table2[[#This Row],[Transaction Date]],"mmmm"),"Unknown") -> June | M33: =IF(ISNUMBER(Table2[[#This Row],[Transaction Date]]),TEXT(Table2[[#This Row],[Transaction Date]],"dddd"),"Unknown") -> Thursday | N33: =IF(OR(B33="",B33="unknown",B33="error",C33="",C33="unknown",C33="error",G33="",G33="error",G33="unknown"),1,0) -> 0 | O33: =IF(OR(C33="",C33="error",C33="unknown"),"Estimated","Actual") -> Actual
A34: TXN_6688524 | B34: Coffee | C34: 4 | D34: =IF(OR(C34="",C34="UNKNOWN",C34="ERROR"),IFERROR(VALUE(G34)/VALUE(E34),""),VALUE(C34)) -> 4 | E34: 2 | F34: =IF(OR(E34="",E34="UNKNOWN",E34="ERROR"),_xlfn.XLOOKUP(Table2[[#This Row],[Item]],Items_List!A:A,Items_List!B:B),E34) -> 2 | G34: 8 | H34: =D34*F34 -> 8 | I34: N/A | J34: N/A | K34: 45106 | L34: =IF(ISNUMBER(Table2[[#This Row],[Transaction Date]]),TEXT(Table2[[#This Row],[Transaction Date]],"mmmm"),"Unknown") -> June | M34: =IF(ISNUMBER(Table2[[#This Row],[Transaction Date]]),TEXT(Table2[[#This Row],[Transaction Date]],"dddd"),"Unknown") -> Thursday | N34: =IF(OR(B34="",B34="unknown",B34="error",C34="",C34="unknown",C34="error",G34="",G34="error",G34="unknown"),1,0) -> 0 | O34: =IF(OR(C34="",C34="error",C34="unknown"),"Estimated","Actual") -> Actual
A35: TXN_2083138 | B35: Smoothie | C35: 3 | D35: =IF(OR(C35="",C35="UNKNOWN",C35="ERROR"),IFERROR(VALUE(G35)/VALUE(E35),""),VALUE(C35)) -> 3 | E35: 4 | F35: =IF(OR(E35="",E35="UNKNOWN",E35="ERROR"),_xlfn.XLOOKUP(Table2[[#This Row],[Item]],Items_List!A:A,Items_List!B:B),E35) -> 4 | G35: 12 | H35: =D35*F35 -> 12 | I35: N/A | J35: In-store | K35: 45033 | L35: =IF(ISNUMBER(Table2[[#This Row],[Transaction Date]]),TEXT(Table2[[#This Row],[Transaction Date]],"mmmm"),"Unknown") -> April | M35: =IF(ISNUMBER(Table2[[#This Row],[Transaction Date]]),TEXT(Table2[[#This Row],[Transaction Date]],"dddd"),"Unknown") -> Monday | N35: =IF(OR(B35="",B35="unknown",B35="error",C35="",C35="unknown",C35="error",G35="",G35="error",G35="unknown"),1,0) -> 0 | O35: =IF(OR(C35="",C35="error",C35="unknown"),"Estimated","Actual") -> Actual
A36: TXN_2427584 | B36: Sandwich | C36: 4 | D36: =IF(OR(C36="",C36="UNKNOWN",C36="ERROR"),IFERROR(VALUE(G36)/VALUE(E36),""),VALUE(C36)) -> 4 | E36: 4 | F36: =IF(OR(E36="",E36="UNKNOWN",E36="ERROR"),_xlfn.XLOOKUP(Table2[[#This Row],[Item]],Items_List!A:A,Items_List!B:B),E36) -> 4 | G36: 16 | H36: =D36*F36 -> 16 | I36: N/A | J36: Takeaway | K36: 45282 | L36: =IF(ISNUMBER(Table2[[#This Row],[Transaction Date]]),TEXT(Table2[[#This Row],[Transaction Date]],"mmmm"),"Unknown") -> December | M36: =IF(ISNUMBER(Table2[[#This Row],[Transaction Date]]),TEXT(Table2[[#This Row],[Transaction Date]],"dddd"),"Unknown") -> Friday | N36: =IF(OR(B36="",B36="unknown",B36="error",C36="",C36="unknown",C36="error",G36="",G36="error",G36="unknown"),1,0) -> 0 | O36: =IF(OR(C36="",C36="error",C36="unknown"),"Estimated","Actual") -> Actual
A37: TXN_6650263 | B37: Tea | C37: 2 | D37: =IF(OR(C37="",C37="UNKNOWN",C37="ERROR"),IFERROR(VALUE(G37)/VALUE(E37),""),VALUE(C37)) -> 2 | E37: 1.5 | F37: =IF(OR(E37="",E37="UNKNOWN",E37="ERROR"),_xlfn.XLOOKUP(Table2[[#This Row],[Item]],Items_List!A:A,Items_List!B:B),E37) -> 1.5 | G37: UNKNOWN | H37: =D37*F37 -> 3 | I37: N/A | J37: Takeaway | K37: 44936 | L37: =IF(ISNUMBER(Table2[[#This Row],[Transaction Date]]),TEXT(Table2[[#This Row],[Transaction Date]],"mmmm"),"Unknown") -> January | M37: =IF(ISNUMBER(Table2[[#This Row],[Transaction Date]]),TEXT(Table2[[#This Row],[Transaction Date]],"dddd"),"Unknown") -> Tuesday | N37: =IF(OR(B37="",B37="unknown",B37="error",C37="",C37="unknown",C37="error",G37="",G37="error",G37="unknown"),1,0) -> 1 | O37: =IF(OR(C37="",C37="error",C37="unknown"),"Estimated","Actual") -> Actual
A38: TXN_9620080 | B38: Juice | C38: 4 | D38: =IF(OR(C38="",C38="UNKNOWN",C38="ERROR"),IFERROR(VALUE(G38)/VALUE(E38),""),VALUE(C38)) -> 4 | E38: 3 | F38: =IF(OR(E38="",E38="UNKNOWN",E38="ERROR"),_xlfn.XLOOKUP(Table2[[#This Row],[Item]],Items_List!A:A,Items_List!B:B),E38) -> 3 | G38: 12 | H38: =D38*F38 -> 12 | I38: N/A | J38: Takeaway | K38: 45201 | L38: =IF(ISNUMBER(Table2[[#This Row],[Transaction Date]]),TEXT(Table2[[#This Row],[Transaction Date]],"mmmm"),"Unknown") -> October | M38: =IF(ISNUMBER(Table2[[#This Row],[Transaction Date]]),TEXT(Table2[[#This Row],[Transaction Date]],"dddd"),"Unknown") -> Monday | N38: =IF(OR(B38="",B38="unknown",B38="error",C38="",C38="unknown",C38="error",G38="",G38="error",G38="unknown"),1,0) -> 0 | O38: =IF(OR(C38="",C38="error",C38="unknown"),"Estimated","Actual") -> Actual
A39: TXN_1491578 | B39: Cookie | C39: 2 | D39: =IF(OR(C39="",C39="UNKNOWN",C39="ERROR"),IFERROR(VALUE(G39)/VALUE(E39),""),VALUE(C39)) -> 2 | E39: 1 | F39: =IF(OR(E39="",E39="UNKNOWN",E39="ERROR"),_xlfn.XLOOKUP(Table2[[#This Row],[Item]],Items_List!A:A,Items_List!B:B),E39) -> 1 | G39: 2 | H39: =D39*F39 -> 2 | I39: N/A | J39: N/A | K39: 44980 | L39: =IF(ISNUMBER(Table2[[#This Row],[Transaction Date]]),TEXT(Table2[[#This Row],[Transaction Date]],"mmmm"),"Unknown") -> February | M39: =IF(ISNUMBER(Table2[[#This Row],[Transaction Date]]),TEXT(Table2[[#This Row],[Transaction Date]],"dddd"),"Unknown") -> Thursday | N39: =IF(OR(B39="",B39="unknown",B39="error",C39="",C39="unknown",C39="error",G39="",G39="error",G39="unknown"),1,0) -> 0 | O39: =IF(OR(C39="",C39="error",C39="unknown"),"Estimated","Actual") -> Actual
A40: TXN_5455792 | B40: Salad | C40: 3 | D40: =IF(OR(C40="",C40="UNKNOWN",C40="ERROR"),IFERROR(VALUE(G40)/VALUE(E40),""),VALUE(C40)) -> 3 | E40: 5 | F40: =IF(OR(E40="",E40="UNKNOWN",E40="ERROR"),_xlfn.XLOOKUP(Table2[[#This Row],[Item]],Items_List!A:A,Items_List!B:B),E40) -> 5 | G40: 15 | H40: =D40*F40 -> 15 | I40: Cash | J40: N/A | K40: 45007 | L40: =IF(ISNUMBER(Table2[[#This Row],[Transaction Date]]),TEXT(Table2[[#This Row],[Transaction Date]],"mmmm"),"Unknown") -> March | M40: =IF(ISNUMBER(Table2[[#This Row],[Transaction Date]]),TEXT(Table2[[#This Row],[Transaction Date]],"dddd"),"Unknown") -> Wednesday | N40: =IF(OR(B40="",B40="unknown",B40="error",C40="",C40="unknown",C40="error",G40="",G40="error",G40="unknown"),1,0) -> 0 | O40: =IF(OR(C40="",C40="error",C40="unknown"),"Estimated","Actual") -> Actual
A41: TXN_8078640 | B41: Juice | C41: 4 | D41: =IF(OR(C41="",C41="UNKNOWN",C41="ERROR"),IFERROR(VALUE(G41)/VALUE(E41),""),VALUE(C41)) -> 4 | E41: 3 | F41: =IF(OR(E41="",E41="UNKNOWN",E41="ERROR"),_xlfn.XLOOKUP(Table2[[#This Row],[Item]],Items_List!A:A,Items_List!B:B),E41) -> 3 | G41: 12 | H41: =D41*F41 -> 12 | I41: Digital Wallet | J41: In-store | K41: 45233 | L41: =IF(ISNUMBER(Table2[[#This Row],[Transaction Date]]),TEXT(Table2[[#This Row],[Transaction Date]],"mmmm"),"Unknown") -> November | M41: =IF(ISNUMBER(Table2[[#This Row],[Transaction Date]]),TEXT(Table2[[#This Row],[Transaction Date]],"dddd"),"Unknown") -> Friday | N41: =IF(OR(B41="",B41="unknown",B41="error",C41="",C41="unknown",C41="error",G41="",G41="error",G41="unknown"),1,0) -> 0 | O41: =IF(OR(C41="",C41="error",C41="unknown"),"Estimated","Actual") -> Actual
A42: TXN_9499313 | B42: Juice | C42: 5 | D42: =IF(OR(C42="",C42="UNKNOWN",C42="ERROR"),IFERROR(VALUE(G42)/VALUE(E42),""),VALUE(C42)) -> 5 | E42: 3 | F42: =IF(OR(E42="",E42="UNKNOWN",E42="ERROR"),_xlfn.XLOOKUP(Table2[[#This Row],[Item]],Items_List!A:A,Items_List!B:B),E42) -> 3 | G42: 15 | H42: =D42*F42 -> 15 | I42: N/A | J42: N/A | K42: 44987 | L42: =IF(ISNUMBER(Table2[[#This Row],[Transaction Date]]),TEXT(Table2[[#This Row],[Transaction Date]],"mmmm"),"Unknown") -> March | M42: =IF(ISNUMBER(Table2[[#This Row],[Transaction Date]]),TEXT(Table2[[#This Row],[Transaction Date]],"dddd"),"Unknown") -> Thursday | N42: =IF(OR(B42="",B42="unknown",B42="error",C42="",C42="unknown",C42="error",G42="",G42="error",G42="unknown"),1,0) -> 0 | O42: =IF(OR(C42="",C42="error",C42="unknown"),"Estimated","Actual") -> Actual
A43: TXN_8201146 | B43: Juice | C43: 5 | D43: =IF(OR(C43="",C43="UNKNOWN",C43="ERROR"),IFERROR(VALUE(G43)/VALUE(E43),""),VALUE(C43)) -> 5 | E43: 3 | F43: =IF(OR(E43="",E43="UNKNOWN",E43="ERROR"),_xlfn.XLOOKUP(Table2[[#This Row],[Item]],Items_List!A:A,Items_List!B:B),E43) -> 3 | G43: 15 | H43: =D43*F43 -> 15 | I43: Cash | J43: N/A | K43: 45103 | L43: =IF(ISNUMBER(Table2[[#This Row],[Transaction Date]]),TEXT(Table2[[#This Row],[Transaction Date]],"mmmm"),"Unknown") -> June | M43: =IF(ISNUMBER(Table2[[#This Row],[Transaction Date]]),TEXT(Table2[[#This Row],[Transaction Date]],"dddd"),"Unknown") -> Monday | N43: =IF(OR(B43="",B43="unknown",B43="error",C43="",C43="unknown",C43="error",G43="",G43="error",G43="unknown"),1,0) -> 0 | O43: =IF(OR(C43="",C43="error",C43="unknown"),"Estimated","Actual") -> Actual
A44: TXN_8230936 | B44: Cake | C44: 3 | D44: =IF(OR(C44="",C44="UNKNOWN",C44="ERROR"),IFERROR(VALUE(G44)/VALUE(E44),""),VALUE(C44)) -> 3 | E44: 3 | F44: =IF(OR(E44="",E44="UNKNOWN",E44="ERROR"),_xlfn.XLOOKUP(Table2[[#This Row],[Item]],Items_List!A:A,Items_List!B:B),E44) -> 3 | G44: 9 | H44: =D44*F44 -> 9 | I44: N/A | J44: N/A | K44: 45048 | L44: =IF(ISNUMBER(Table2[[#This Row],[Transaction Date]]),TEXT(Table2[[#This Row],[Transaction Date]],"mmmm"),"Unknown") -> May | M44: =IF(ISNUMBER(Table2[[#This Row],[Transaction Date]]),TEXT(Table2[[#This Row],[Transaction Date]],"dddd"),"Unknown") -> Tuesday | N44: =IF(OR(B44="",B44="unknown",B44="error",C44="",C44="unknown",C44="error",G44="",G44="error",G44="unknown"),1,0) -> 0 | O44: =IF(OR(C44="",C44="error",C44="unknown"),"Estimated","Actual") -> Actual
A45: TXN_7742742 | B45: Cake | C45: 5 | D45: =IF(OR(C45="",C45="UNKNOWN",C45="ERROR"),IFERROR(VALUE(G45)/VALUE(E45),""),VALUE(C45)) -> 5 | E45: 3 | F45: =IF(OR(E45="",E45="UNKNOWN",E45="ERROR"),_xlfn.XLOOKUP(Table2[[#This Row],[Item]],Items_List!A:A,Items_List!B:B),E45) -> 3 | G45: 15 | H45: =D45*F45 -> 15 | I45: N/A | J45: Takeaway | K45: 45174 | L45: =IF(ISNUMBER(Table2[[#This Row],[Transaction Date]]),TEXT(Table2[[#This Row],[Transaction Date]],"mmmm"),"Unknown") -> September | M45: =IF(ISNUMBER(Table2[[#This Row],[Transaction Date]]),TEXT(Table2[[#This Row],[Transaction Date]],"dddd"),"Unknown") -> Tuesday | N45: =IF(OR(B45="",B45="unknown",B45="error",C45="",C45="unknown",C45="error",G45="",G45="error",G45="unknown"),1,0) -> 0 | O45: =IF(OR(C45="",C45="error",C45="unknown"),"Estimated","Actual") -> Actual
A46: TXN_6342161 | B46: Salad | C46: 5 | D46: =IF(OR(C46="",C46="UNKNOWN",C46="ERROR"),IFERROR(VALUE(G46)/VALUE(E46),""),VALUE(C46)) -> 5 | E46: 5 | F46: =IF(OR(E46="",E46="UNKNOWN",E46="ERROR"),_xlfn.XLOOKUP(Table2[[#This Row],[Item]],Items_List!A:A,Items_List!B:B),E46) -> 5 | G46: 25 | H46: =D46*F46 -> 25 | I46: N/A | J46: Takeaway | K46: 44934 | L46: =IF(ISNUMBER(Table2[[#This Row],[Transaction Date]]),TEXT(Table2[[#This Row],[Transaction Date]],"mmmm"),"Unknown") -> January | M46: =IF(ISNUMBER(Table2[[#This Row],[Transaction Date]]),TEXT(Table2[[#This Row],[Transaction Date]],"dddd"),"Unknown") -> Sunday | N46: =IF(OR(B46="",B46="unknown",B46="error",C46="",C46="unknown",C46="error",G46="",G46="error",G46="unknown"),1,0) -> 0 | O46: =IF(OR(C46="",C46="error",C46="unknown"),"Estimated","Actual") -> Actual
A47: TXN_3363746 | B47: Smoothie | C47: 3 | D47: =IF(OR(C47="",C47="UNKNOWN",C47="ERROR"),IFERROR(VALUE(G47)/VALUE(E47),""),VALUE(C47)) -> 3 | E47: 4 | F47: =IF(OR(E47="",E47="UNKNOWN",E47="ERROR"),_xlfn.XLOOKUP(Table2[[#This Row],[Item]],Items_List!A:A,Items_List!B:B),E47) -> 4 | G47: 12 | H47: =D47*F47 -> 12 | I47: Credit Card | J47: N/A | K47: 45255 | L47: =IF(ISNUMBER(Table2[[#This Row],[Transaction Date]]),TEXT(Table2[[#This Row],[Transaction Date]],"mmmm"),"Unknown") -> November | M47: =IF(ISNUMBER(Table2[[#This Row],[Transaction Date]]),TEXT(Table2[[#This Row],[Transaction Date]],"dddd"),"Unknown") -> Saturday | N47: =IF(OR(B47="",B47="unknown",B47="error",C47="",C47="unknown",C47="error",G47="",G47="error",G47="unknown"),1,0) -> 0 | O47: =IF(OR(C47="",C47="error",C47="unknown"),"Estimated","Actual") -> Actual
A48: TXN_8614868 | B48: Smoothie | C48: 5 | D48: =IF(OR(C48="",C48="UNKNOWN",C48="ERROR"),IFERROR(VALUE(G48)/VALUE(E48),""),VALUE(C48)) -> 5 | E48: 4 | F48: =IF(OR(E48="",E48="UNKNOWN",E48="ERROR"),_xlfn.XLOOKUP(Table2[[#This Row],[Item]],Items_List!A:A,Items_List!B:B),E48) -> 4 | G48: 20 | H48: =D48*F48 -> 20 | I48: Digital Wallet | J48: Takeaway | K48: 45265 | L48: =IF(ISNUMBER(Table2[[#This Row],[Transaction Date]]),TEXT(Table2[[#This Row],[Transaction Date]],"mmmm"),"Unknown") -> December | M48: =IF(ISNUMBER(Table2[[#This Row],[Transaction Date]]),TEXT(Table2[[#This Row],[Transaction Date]],"dddd"),"Unknown") -> Tuesday | N48: =IF(OR(B48="",B48="unknown",B48="error",C48="",C48="unknown",C48="error",G48="",G48="error",G48="unknown"),1,0) -> 0 | O48: =IF(OR(C48="",C48="error",C48="unknown"),"Estimated","Actual") -> Actual
A49: TXN_5522862 | B49: Cookie | C49: ERROR | D49: =IF(OR(C49="",C49="UNKNOWN",C49="ERROR"),IFERROR(VALUE(G49)/VALUE(E49),""),VALUE(C49)) -> 2 | E49: 1 | F49: =IF(OR(E49="",E49="UNKNOWN",E49="ERROR"),_xlfn.XLOOKUP(Table2[[#This Row],[Item]],Items_List!A:A,Items_List!B:B),E49) -> 1 | G49: 2 | H49: =D49*F49 -> 2 | I49: Credit Card | J49: Takeaway | K49: 45004 | L49: =IF(ISNUMBER(Table2[[#This Row],[Transaction Date]]),TEXT(Table2[[#This Row],[Transaction Date]],"mmmm"),"Unknown") -> March | M49: =IF(ISNUMBER(Table2[[#This Row],[Transaction Date]]),TEXT(Table2[[#This Row],[Transaction Date]],"dddd"),"Unknown") -> Sunday | N49: =IF(OR(B49="",B49="unknown",B49="error",C49="",C49="unknown",C49="error",G49="",G49="error",G49="unknown"),1,0) -> 1 | O49: =IF(OR(C49="",C49="error",C49="unknown"),"Estimated","Actual") -> Estimated
A50: TXN_3578141 | B50: Cake | C50: 5 | D50: =IF(OR(C50="",C50="UNKNOWN",C50="ERROR"),IFERROR(VALUE(G50)/VALUE(E50),""),VALUE(C50)) -> 5 | E50: =_xlfn.XLOOKUP(Table2[[#This Row],[Item]],Items_List!$A$2:$A$9,Items_List!$B$2:$B$9) -> 3 | F50: =IF(OR(E50="",E50="UNKNOWN",E50="ERROR"),_xlfn.XLOOKUP(Table2[[#This Row],[Item]],Items_List!A:A,Items_List!B:B),E50) -> 3 | G50: 15 | H50: =D50*F50 -> 15 | I50: N/A | J50: Takeaway | K50: 45104 | L50: =IF(ISNUMBER(Table2[[#This Row],[Transaction Date]]),TEXT(Table2[[#This Row],[Transaction Date]],"mmmm"),"Unknown") -> June | M50: =IF(ISNUMBER(Table2[[#This Row],[Transaction Date]]),TEXT(Table2[[#This Row],[Transaction Date]],"dddd"),"Unknown") -> Tuesday | N50: =IF(OR(B50="",B50="unknown",B50="error",C50="",C50="unknown",C50="error",G50="",G50="error",G50="unknown"),1,0) -> 0 | O50: =IF(OR(C50="",C50="error",C50="unknown"),"Estimated","Actual") -> Actual
A51: TXN_2080895 | B51: Cake | C51: UNKNOWN | D51: =IF(OR(C51="",C51="UNKNOWN",C51="ERROR"),IFERROR(VALUE(G51)/VALUE(E51),""),VALUE(C51)) -> 1 | E51: 3 | F51: =IF(OR(E51="",E51="UNKNOWN",E51="ERROR"),_xlfn.XLOOKUP(Table2[[#This Row],[Item]],Items_List!A:A,Items_List!B:B),E51) -> 3 | G51: 3 | H51: =D51*F51 -> 3 | I51: Digital Wallet | J51: In-store | K51: 45035 | L51: =IF(ISNUMBER(Table2[[#This Row],[Transaction Date]]),TEXT(Table2[[#This Row],[Transaction Date]],"mmmm"),"Unknown") -> April | M51: =IF(ISNUMBER(Table2[[#This Row],[Transaction Date]]),TEXT(Table2[[#This Row],[Transaction Date]],"dddd"),"Unknown") -> Wednesday | N51: =IF(OR(B51="",B51="unknown",B51="error",C51="",C51="unknown",C51="error",G51="",G51="error",G51="unknown"),1,0) -> 1 | O51: =IF(OR(C51="",C51="error",C51="unknown"),"Estimated","Actual") -> Estimated
A52: TXN_6421134 | B52: Sandwich | C52: 4 | D52: =IF(OR(C52="",C52="UNKNOWN",C52="ERROR"),IFERROR(VALUE(G52)/VALUE(E52),""),VALUE(C52)) -> 4 | E52: 4 | F52: =IF(OR(E52="",E52="UNKNOWN",E52="ERROR"),_xlfn.XLOOKUP(Table2[[#This Row],[Item]],Items_List!A:A,Items_List!B:B),E52) -> 4 | G52: 16 | H52: =D52*F52 -> 16 | I52: Cash | J52: Takeaway | K52: 45233 | L52: =IF(ISNUMBER(Table2[[#This Row],[Transaction Date]]),TEXT(Table2[[#This Row],[Transaction Date]],"mmmm"),"Unknown") -> November | M52: =IF(ISNUMBER(Table2[[#This Row],[Transaction Date]]),TEXT(Table2[[#This Row],[Transaction Date]],"dddd"),"Unknown") -> Friday | N52: =IF(OR(B52="",B52="unknown",B52="error",C52="",C52="unknown",C52="error",G52="",G52="error",G52="unknown"),1,0) -> 0 | O52: =IF(OR(C52="",C52="error",C52="unknown"),"Estimated","Actual") -> Actual
A53: TXN_8813311 | B53: Juice | C53: 5 | D53: =IF(OR(C53="",C53="UNKNOWN",C53="ERROR"),IFERROR(VALUE(G53)/VALUE(E53),""),VALUE(C53)) -> 5 | E53: 3 | F53: =IF(OR(E53="",E53="UNKNOWN",E53="ERROR"),_xlfn.XLOOKUP(Table2[[#This Row],[Item]],Items_List!A:A,Items_List!B:B),E53) -> 3 | G53: 15 | H53: =D53*F53 -> 15 | I53: N/A | J53: In-store | K53: 45206 | L53: =IF(ISNUMBER(Table2[[#This Row],[Transaction Date]]),TEXT(Table2[[#This Row],[Transaction Date]],"mmmm"),"Unknown") -> October | M53: =IF(ISNUMBER(Table2[[#This Row],[Transaction Date]]),TEXT(Table2[[#This Row],[Transaction Date]],"dddd"),"Unknown") -> Saturday | N53: =IF(OR(B53="",B53="unknown",B53="error",C53="",C53="unknown",C53="error",G53="",G53="error",G53="unknown"),1,0) -> 0 | O53: =IF(OR(C53="",C53="error",C53="unknown"),"Estimated","Actual") -> Actual
A54: TXN_9023317 | B54: Salad | C54: 1 | D54: =IF(OR(C54="",C54="UNKNOWN",C54="ERROR"),IFERROR(VALUE(G54)/VALUE(E54),""),VALUE(C54)) -> 1 | E54: 5 | F54: =IF(OR(E54="",E54="UNKNOWN",E54="ERROR"),_xlfn.XLOOKUP(Table2[[#This Row],[Item]],Items_List!A:A,Items_List!B:B),E54) -> 5 | G54: 5 | H54: =D54*F54 -> 5 | I54: N/A | J54: N/A | K54: 45199 | L54: =IF(ISNUMBER(Table2[[#This Row],[Transaction Date]]),TEXT(Table2[[#This Row],[Transaction Date]],"mmmm"),"Unknown") -> September | M54: =IF(ISNUMBER(Table2[[#This Row],[Transaction Date]]),TEXT(Table2[[#This Row],[Transaction Date]],"dddd"),"Unknown") -> Saturday | N54: =IF(OR(B54="",B54="unknown",B54="error",C54="",C54="unknown",C54="error",G54="",G54="error",G54="unknown"),1,0) -> 0 | O54: =IF(OR(C54="",C54="error",C54="unknown"),"Estimated","Actual") -> Actual
A55: TXN_2537617 | B55: Sandwich | C55: 1 | D55: =IF(OR(C55="",C55="UNKNOWN",C55="ERROR"),IFERROR(VALUE(G55)/VALUE(E55),""),VALUE(C55)) -> 1 | E55: 4 | F55: =IF(OR(E55="",E55="UNKNOWN",E55="ERROR"),_xlfn.XLOOKUP(Table2[[#This Row],[Item]],Items_List!A:A,Items_List!B:B),E55) -> 4 | G55: 4 | H55: =D55*F55 -> 4 | I55: Cash | J55: N/A | K55: 45073 | L55: =IF(ISNUMBER(Table2[[#This Row],[Transaction Date]]),TEXT(Table2[[#This Row],[Transaction Date]],"mmmm"),"Unknown") -> May | M55: =IF(ISNUMBER(Table2[[#This Row],[Transaction Date]]),TEXT(Table2[[#This Row],[Transaction Date]],"dddd"),"Unknown") -> Saturday | N55: =IF(OR(B55="",B55="unknown",B55="error",C55="",C55="unknown",C55="error",G55="",G55="error",G55="unknown"),1,0) -> 0 | O55: =IF(OR(C55="",C55="error",C55="unknown"),"Estimated","Actual") -> Actual
A56: TXN_9230615 | B56: Smoothie | C56: 4 | D56: =IF(OR(C56="",C56="UNKNOWN",C56="ERROR"),IFERROR(VALUE(G56)/VALUE(E56),""),VALUE(C56)) -> 4 | E56: 4 | F56: =IF(OR(E56="",E56="UNKNOWN",E56="ERROR"),_xlfn.XLOOKUP(Table2[[#This Row],[Item]],Items_List!A:A,Items_List!B:B),E56) -> 4 | G56: 16 | H56: =D56*F56 -> 16 | I56: Digital Wallet | J56: N/A | K56: 45078 | L56: =IF(ISNUMBER(Table2[[#This Row],[Transaction Date]]),TEXT(Table2[[#This Row],[Transaction Date]],"mmmm"),"Unknown") -> June | M56: =IF(ISNUMBER(Table2[[#This Row],[Transaction Date]]),TEXT(Table2[[#This Row],[Transaction Date]],"dddd"),"Unknown") -> Thursday | N56: =IF(OR(B56="",B56="unknown",B56="error",C56="",C56="unknown",C56="error",G56="",G56="error",G56="unknown"),1,0) -> 0 | O56: =IF(OR(C56="",C56="error",C56="unknown"),"Estimated","Actual") -> Actual
A57: TXN_4987129 | B57: Sandwich | C57: 3 | D57: =IF(OR(C57="",C57="UNKNOWN",C57="ERROR"),IFERROR(VALUE(G57)/VALUE(E57),""),VALUE(C57)) -> 3 | E57: =_xlfn.XLOOKUP(Table2[[#This Row],[Item]],Items_List!$A$2:$A$9,Items_List!$B$2:$B$9) -> 4 | F57: =IF(OR(E57="",E57="UNKNOWN",E57="ERROR"),_xlfn.XLOOKUP(Table2[[#This Row],[Item]],Items_List!A:A,Items_List!B:B),E57) -> 4 | H57: =D57*F57 -> 12 | I57: N/A | J57: In-store | K57: 45219 | L57: =IF(ISNUMBER(Table2[[#This Row],[Transaction Date]]),TEXT(Table2[[#This Row],[Transaction Date]],"mmmm"),"Unknown") -> October | M57: =IF(ISNUMBER(Table2[[#This Row],[Transaction Date]]),TEXT(Table2[[#This Row],[Transaction Date]],"dddd"),"Unknown") -> Friday | N57: =IF(OR(B57="",B57="unknown",B57="error",C57="",C57="unknown",C57="error",G57="",G57="error",G57="unknown"),1,0) -> 1 | O57: =IF(OR(C57="",C57="error",C57="unknown"),"Estimated","Actual") -> Actual
A58: TXN_8501819 | B58: Juice | D58: =IF(OR(C58="",C58="UNKNOWN",C58="ERROR"),IFERROR(VALUE(G58)/VALUE(E58),""),VALUE(C58)) -> 2 | E58: 3 | F58: =IF(OR(E58="",E58="UNKNOWN",E58="ERROR"),_xlfn.XLOOKUP(Table2[[#This Row],[Item]],Items_List!A:A,Items_List!B:B),E58) -> 3 | G58: 6 | H58: =D58*F58 -> 6 | I58: Cash | J58: N/A | K58: 45015 | L58: =IF(ISNUMBER(Table2[[#This Row],[Transaction Date]]),TEXT(Table2[[#This Row],[Transaction Date]],"mmmm"),"Unknown") -> March | M58: =IF(ISNUMBER(Table2[[#This Row],[Transaction Date]]),TEXT(Table2[[#This Row],[Transaction Date]],"dddd"),"Unknown") -> Thursday | N58: =IF(OR(B58="",B58="unknown",B58="error",C58="",C58="unknown",C58="error",G58="",G58="error",G58="unknown"),1,0) -> 1 | O58: =IF(OR(C58="",C58="error",C58="unknown"),"Estimated","Actual") -> Estimated
A59: TXN_3068204 | B59: Cookie | C59: 1 | D59: =IF(OR(C59="",C59="UNKNOWN",C59="ERROR"),IFERROR(VALUE(G59)/VALUE(E59),""),VALUE(C59)) -> 1 | E59: 1 | F59: =IF(OR(E59="",E59="UNKNOWN",E59="ERROR"),_xlfn.XLOOKUP(Table2[[#This Row],[Item]],Items_List!A:A,Items_List!B:B),E59) -> 1 | G59: 1 | H59: =D59*F59 -> 1 | I59: Credit Card | J59: Takeaway | K59: 45202 | L59: =IF(ISNUMBER(Table2[[#This Row],[Transaction Date]]),TEXT(Table2[[#This Row],[Transaction Date]],"mmmm"),"Unknown") -> October | M59: =IF(ISNUMBER(Table2[[#This Row],[Transaction Date]]),TEXT(Table2[[#This Row],[Transaction Date]],"dddd"),"Unknown") -> Tuesday | N59: =IF(OR(B59="",B59="unknown",B59="error",C59="",C59="unknown",C59="error",G59="",G59="error",G59="unknown"),1,0) -> 0 | O59: =IF(OR(C59="",C59="error",C59="unknown"),"Estimated","Actual") -> Actual
A60: TXN_8427104 | B60: Salad | C60: 2 | D60: =IF(OR(C60="",C60="UNKNOWN",C60="ERROR"),IFERROR(VALUE(G60)/VALUE(E60),""),VALUE(C60)) -> 2 | E60: =_xlfn.XLOOKUP(Table2[[#This Row],[Item]],Items_List!$A$2:$A$9,Items_List!$B$2:$B$9) -> 5 | F60: =IF(OR(E60="",E60="UNKNOWN",E60="ERROR"),_xlfn.XLOOKUP(Table2[[#This Row],[Item]],Items_List!A:A,Items_List!B:B),E60) -> 5 | G60: 10 | H60: =D60*F60 -> 10 | I60: N/A | J60: In-store | K60: 45226 | L60: =IF(ISNUMBER(Table2[[#This Row],[Transaction Date]]),TEXT(Table2[[#This Row],[Transaction Date]],"mmmm"),"Unknown") -> October | M60: =IF(ISNUMBER(Table2[[#This Row],[Transaction Date]]),TEXT(Table2[[#This Row],[Transaction Date]],"dddd"),"Unknown") -> Friday | N60: =IF(OR(B60="",B60="unknown",B60="error",C60="",C60="unknown",C60="error",G60="",G60="error",G60="unknown"),1,0) -> 0 | O60: =IF(OR(C60="",C60="error",C60="unknown"),"Estimated","Actual") -> Actual
A61: TXN_2621580 | B61: Tea | C61: 2 | D61: =IF(OR(C61="",C61="UNKNOWN",C61="ERROR"),IFERROR(VALUE(G61)/VALUE(E61),""),VALUE(C61)) -> 2 | E61: 1.5 | F61: =IF(OR(E61="",E61="UNKNOWN",E61="ERROR"),_xlfn.XLOOKUP(Table2[[#This Row],[Item]],Items_List!A:A,Items_List!B:B),E61) -> 1.5 | G61: 3 | H61: =D61*F61 -> 3 | I61: Cash | J61: In-store | K61: 45007 | L61: =IF(ISNUMBER(Table2[[#This Row],[Transaction Date]]),TEXT(Table2[[#This Row],[Transaction Date]],"mmmm"),"Unknown") -> March | M61: =IF(ISNUMBER(Table2[[#This Row],[Transaction Date]]),TEXT(Table2[[#This Row],[Transaction Date]],"dddd"),"Unknown") -> Wednesday | N61: =IF(OR(B61="",B61="unknown",B61="error",C61="",C61="unknown",C61="error",G61="",G61="error",G61="unknown"),1,0) -> 0 | O61: =IF(OR(C61="",C61="error",C61="unknown"),"Estimated","Actual") -> Actual
A62: TXN_4726376 | B62: Cake | C62: 2 | D62: =IF(OR(C62="",C62="UNKNOWN",C62="ERROR"),IFERROR(VALUE(G62)/VALUE(E62),""),VALUE(C62)) -> 2 | E62: 3 | F62: =IF(OR(E62="",E62="UNKNOWN",E62="ERROR"),_xlfn.XLOOKUP(Table2[[#This Row],[Item]],Items_List!A:A,Items_List!B:B),E62) -> 3 | G62: 6 | H62: =D62*F62 -> 6 | I62: Credit Card | J62: In-store | K62: 44957 | L62: =IF(ISNUMBER(Table2[[#This Row],[Transaction Date]]),TEXT(Table2[[#This Row],[Transaction Date]],"mmmm"),"Unknown") -> January | M62: =IF(ISNUMBER(Table2[[#This Row],[Transaction Date]]),TEXT(Table2[[#This Row],[Transaction Date]],"dddd"),"Unknown") -> Tuesday | N62: =IF(OR(B62="",B62="unknown",B62="error",C62="",C62="unknown",C62="error",G62="",G62="error",G62="unknown"),1,0) -> 0 | O62: =IF(OR(C62="",C62="error",C62="unknown"),"Estimated","Actual") -> Actual
A63: TXN_4238417 | B63: Salad | C63: 2 | D63: =IF(OR(C63="",C63="UNKNOWN",C63="ERROR"),IFERROR(VALUE(G63)/VALUE(E63),""),VALUE(C63)) -> 2 | E63: 5 | F63: =IF(OR(E63="",E63="UNKNOWN",E63="ERROR"),_xlfn.XLOOKUP(Table2[[#This Row],[Item]],Items_List!A:A,Items_List!B:B),E63) -> 5 | G63: 10 | H63: =D63*F63 -> 10 | I63: N/A | J63: N/A | K63: 45096 | L63: =IF(ISNUMBER(Table2[[#This Row],[Transaction Date]]),TEXT(Table2[[#This Row],[Transaction Date]],"mmmm"),"Unknown") -> June | M63: =IF(ISNUMBER(Table2[[#This Row],[Transaction Date]]),TEXT(Table2[[#This Row],[Transaction Date]],"dddd"),"Unknown") -> Monday | N63: =IF(OR(B63="",B63="unknown",B63="error",C63="",C63="unknown",C63="error",G63="",G63="error",G63="unknown"),1,0) -> 0 | O63: =IF(OR(C63="",C63="error",C63="unknown"),"Estimated","Actual") -> Actual
A64: TXN_1900620 | B64: Smoothie | C64: 2 | D64: =IF(OR(C64="",C64="UNKNOWN",C64="ERROR"),IFERROR(VALUE(G64)/VALUE(E64),""),VALUE(C64)) -> 2 | E64: 4 | F64: =IF(OR(E64="",E64="UNKNOWN",E64="ERROR"),_xlfn.XLOOKUP(Table2[[#This Row],[Item]],Items_List!A:A,Items_List!B:B),E64) -> 4 | G64: 8 | H64: =D64*F64 -> 8 | I64: Credit Card | J64: N/A | K64: 45274 | L64: =IF(ISNUMBER(Table2[[#This Row],[Transaction Date]]),TEXT(Table2[[#This Row],[Transaction Date]],"mmmm"),"Unknown") -> December | M64: =IF(ISNUMBER(Table2[[#This Row],[Transaction Date]]),TEXT(Table2[[#This Row],[Transaction Date]],"dddd"),"Unknown") -> Thursday | N64: =IF(OR(B64="",B64="unknown",B64="error",C64="",C64="unknown",C64="error",G64="",G64="error",G64="unknown"),1,0) -> 0 | O64: =IF(OR(C64="",C64="error",C64="unknown"),"Estimated","Actual") -> Actual
A65: TXN_6420335 | B65: Coffee | C65: 1 | D65: =IF(OR(C65="",C65="UNKNOWN",C65="ERROR"),IFERROR(VALUE(G65)/VALUE(E65),""),VALUE(C65)) -> 1 | E65: 2 | F65: =IF(OR(E65="",E65="UNKNOWN",E65="ERROR"),_xlfn.XLOOKUP(Table2[[#This Row],[Item]],Items_List!A:A,Items_List!B:B),E65) -> 2 | G65: 2 | H65: =D65*F65 -> 2 | I65: Cash | J65: Takeaway | K65: 45123 | L65: =IF(ISNUMBER(Table2[[#This Row],[Transaction Date]]),TEXT(Table2[[#This Row],[Transaction Date]],"mmmm"),"Unknown") -> July | M65: =IF(ISNUMBER(Table2[[#This Row],[Transaction Date]]),TEXT(Table2[[#This Row],[Transaction Date]],"dddd"),"Unknown") -> Sunday | N65: =IF(OR(B65="",B65="unknown",B65="error",C65="",C65="unknown",C65="error",G65="",G65="error",G65="unknown"),1,0) -> 0 | O65: =IF(OR(C65="",C65="error",C65="unknown"),"Estimated","Actual") -> Actual
A66: TXN_3858209 | B66: Sandwich | C66: 4 | D66: =IF(OR(C66="",C66="UNKNOWN",C66="ERROR"),IFERROR(VALUE(G66)/VALUE(E66),""),VALUE(C66)) -> 4 | E66: 4 | F66: =IF(OR(E66="",E66="UNKNOWN",E66="ERROR"),_xlfn.XLOOKUP(Table2[[#This Row],[Item]],Items_List!A:A,Items_List!B:B),E66) -> 4 | G66: 16 | H66: =D66*F66 -> 16 | I66: Cash | J66: N/A | K66: 44979 | L66: =IF(ISNUMBER(Table2[[#This Row],[Transaction Date]]),TEXT(Table2[[#This Row],[Transaction Date]],"mmmm"),"Unknown") -> February | M66: =IF(ISNUMBER(Table2[[#This Row],[Transaction Date]]),TEXT(Table2[[#This Row],[Transaction Date]],"dddd"),"Unknown") -> Wednesday | N66: =IF(OR(B66="",B66="unknown",B66="error",C66="",C66="unknown",C66="error",G66="",G66="error",G66="unknown"),1,0) -> 0 | O66: =IF(OR(C66="",C66="error",C66="unknown"),"Estimated","Actual") -> Actual
A67: TXN_2091733 | B67: Salad | C67: 1 | D67: =IF(OR(C67="",C67="UNKNOWN",C67="ERROR"),IFERROR(VALUE(G67)/VALUE(E67),""),VALUE(C67)) -> 1 | E67: 5 | F67: =IF(OR(E67="",E67="UNKNOWN",E67="ERROR"),_xlfn.XLOOKUP(Table2[[#This Row],[Item]],Items_List!A:A,Items_List!B:B),E67) -> 5 | G67: 5 | H67: =D67*F67 -> 5 | I67: N/A | J67: In-store | L67: =IF(ISNUMBER(Table2[[#This Row],[Transaction Date]]),TEXT(Table2[[#This Row],[Transaction Date]],"mmmm"),"Unknown") -> Unknown | M67: =IF(ISNUMBER(Table2[[#This Row],[Transaction Date]]),TEXT(Table2[[#This Row],[Transaction Date]],"dddd"),"Unknown") -> Unknown | N67: =IF(OR(B67="",B67="unknown",B67="error",C67="",C67="unknown",C67="error",G67="",G67="error",G67="unknown"),1,0) -> 0 | O67: =IF(OR(C67="",C67="error",C67="unknown"),"Estimated","Actual") -> Actual
A68: TXN_8735480 | B68: Tea | C68: 5 | D68: =IF(OR(C68="",C68="UNKNOWN",C68="ERROR"),IFERROR(VALUE(G68)/VALUE(E68),""),VALUE(C68)) -> 5 | E68: 1.5 | F68: =IF(OR(E68="",E68="UNKNOWN",E68="ERROR"),_xlfn.XLOOKUP(Table2[[#This Row],[Item]],Items_List!A:A,Items_List!B:B),E68) -> 1.5 | G68: 7.5 | H68: =D68*F68 -> 7.5 | I68: Cash | J68: N/A | K68: 45079 | L68: =IF(ISNUMBER(Table2[[#This Row],[Transaction Date]]),TEXT(Table2[[#This Row],[Transaction Date]],"mmmm"),"Unknown") -> June | M68: =IF(ISNUMBER(Table2[[#This Row],[Transaction Date]]),TEXT(Table2[[#This Row],[Transaction Date]],"dddd"),"Unknown") -> Friday | N68: =IF(OR(B68="",B68="unknown",B68="error",C68="",C68="unknown",C68="error",G68="",G68="error",G68="unknown"),1,0) -> 0 | O68: =IF(OR(C68="",C68="error",C68="unknown"),"Estimated","Actual") -> Actual
A69: TXN_3829165 | B69: Juice | C69: 4 | D69: =IF(OR(C69="",C69="UNKNOWN",C69="ERROR"),IFERROR(VALUE(G69)/VALUE(E69),""),VALUE(C69)) -> 4 | E69: 3 | F69: =IF(OR(E69="",E69="UNKNOWN",E69="ERROR"),_xlfn.XLOOKUP(Table2[[#This Row],[Item]],Items_List!A:A,Items_List!B:B),E69) -> 3 | G69: 12 | H69: =D69*F69 -> 12 | I69: Cash | J69: In-store | K69: 45092 | L69: =IF(ISNUMBER(Table2[[#This Row],[Transaction Date]]),TEXT(Table2[[#This Row],[Transaction Date]],"mmmm"),"Unknown") -> June | M69: =IF(ISNUMBER(Table2[[#This Row],[Transaction Date]]),TEXT(Table2[[#This Row],[Transaction Date]],"dddd"),"Unknown") -> Thursday | N69: =IF(OR(B69="",B69="unknown",B69="error",C69="",C69="unknown",C69="error",G69="",G69="error",G69="unknown"),1,0) -> 0 | O69: =IF(OR(C69="",C69="error",C69="unknown"),"Estimated","Actual") -> Actual
A70: TXN_3748616 | B70: Coffee | C70: 2 | D70: =IF(OR(C70="",C70="UNKNOWN",C70="ERROR"),IFERROR(VALUE(G70)/VALUE(E70),""),VALUE(C70)) -> 2 | E70: 2 | F70: =IF(OR(E70="",E70="UNKNOWN",E70="ERROR"),_xlfn.XLOOKUP(Table2[[#This Row],[Item]],Items_List!A:A,Items_List!B:B),E70) -> 2 | G70: 4 | H70: =D70*F70 -> 4 | I70: Credit Card | J70: In-store | K70: 45269 | L70: =IF(ISNUMBER(Table2[[#This Row],[Transaction Date]]),TEXT(Table2[[#This Row],[Transaction Date]],"mmmm"),"Unknown") -> December | M70: =IF(ISNUMBER(Table2[[#This Row],[Transaction Date]]),TEXT(Table2[[#This Row],[Transaction Date]],"dddd"),"Unknown") -> Saturday | N70: =IF(OR(B70="",B70="unknown",B70="error",C70="",C70="unknown",C70="error",G70="",G70="error",G70="unknown"),1,0) -> 0 | O70: =IF(OR(C70="",C70="error",C70="unknown"),"Estimated","Actual") -> Actual
A71: TXN_1993289 | B71: Sandwich | C71: 2 | D71: =IF(OR(C71="",C71="UNKNOWN",C71="ERROR"),IFERROR(VALUE(G71)/VALUE(E71),""),VALUE(C71)) -> 2 | E71: 4 | F71: =IF(OR(E71="",E71="UNKNOWN",E71="ERROR"),_xlfn.XLOOKUP(Table2[[#This Row],[Item]],Items_List!A:A,Items_List!B:B),E71) -> 4 | G71: 8 | H71: =D71*F71 -> 8 | I71: N/A | J71: In-store | K71: 45034 | L71: =IF(ISNUMBER(Table2[[#This Row],[Transaction Date]]),TEXT(Table2[[#This Row],[Transaction Date]],"mmmm"),"Unknown") -> April | M71: =IF(ISNUMBER(Table2[[#This Row],[Transaction Date]]),TEXT(Table2[[#This Row],[Transaction Date]],"dddd"),"Unknown") -> Tuesday | N71: =IF(OR(B71="",B71="unknown",B71="error",C71="",C71="unknown",C71="error",G71="",G71="error",G71="unknown"),1,0) -> 0 | O71: =IF(OR(C71="",C71="error",C71="unknown"),"Estimated","Actual") -> Actual
A72: TXN_2123367 | B72: Cookie | C72: 2 | D72: =IF(OR(C72="",C72="UNKNOWN",C72="ERROR"),IFERROR(VALUE(G72)/VALUE(E72),""),VALUE(C72)) -> 2 | E72: 1 | F72: =IF(OR(E72="",E72="UNKNOWN",E72="ERROR"),_xlfn.XLOOKUP(Table2[[#This Row],[Item]],Items_List!A:A,Items_List!B:B),E72) -> 1 | G72: 2 | H72: =D72*F72 -> 2 | I72: N/A | J72: N/A | K72: 45237 | L72: =IF(ISNUMBER(Table2[[#This Row],[Transaction Date]]),TEXT(Table2[[#This Row],[Transaction Date]],"mmmm"),"Unknown") -> November | M72: =IF(ISNUMBER(Table2[[#This Row],[Transaction Date]]),TEXT(Table2[[#This Row],[Transaction Date]],"dddd"),"Unknown") -> Tuesday | N72: =IF(OR(B72="",B72="unknown",B72="error",C72="",C72="unknown",C72="error",G72="",G72="error",G72="unknown"),1,0) -> 0 | O72: =IF(OR(C72="",C72="error",C72="unknown"),"Estimated","Actual") -> Actual
A73: TXN_5266394 | B73: Cake | C73: 3 | D73: =IF(OR(C73="",C73="UNKNOWN",C73="ERROR"),IFERROR(VALUE(G73)/VALUE(E73),""),VALUE(C73)) -> 3 | E73: 3 | F73: =IF(OR(E73="",E73="UNKNOWN",E73="ERROR"),_xlfn.XLOOKUP(Table2[[#This Row],[Item]],Items_List!A:A,Items_List!B:B),E73) -> 3 | G73: 9 | H73: =D73*F73 -> 9 | I73: Cash | J73: In-store | K73: 45227 | L73: =IF(ISNUMBER(Table2[[#This Row],[Transaction Date]]),TEXT(Table2[[#This Row],[Transaction Date]],"mmmm"),"Unknown") -> October | M73: =IF(ISNUMBER(Table2[[#This Row],[Transaction Date]]),TEXT(Table2[[#This Row],[Transaction Date]],"dddd"),"Unknown") -> Saturday | N73: =IF(OR(B73="",B73="unknown",B73="error",C73="",C73="unknown",C73="error",G73="",G73="error",G73="unknown"),1,0) -> 0 | O73: =IF(OR(C73="",C73="error",C73="unknown"),"Estimated","Actual") -> Actual
A74: TXN_5107946 | B74: Cake | C74: 4 | D74: =IF(OR(C74="",C74="UNKNOWN",C74="ERROR"),IFERROR(VALUE(G74)/VALUE(E74),""),VALUE(C74)) -> 4 | E74: 3 | F74: =IF(OR(E74="",E74="UNKNOWN",E74="ERROR"),_xlfn.XLOOKUP(Table2[[#This Row],[Item]],Items_List!A:A,Items_List!B:B),E74) -> 3 | G74: 12 | H74: =D74*F74 -> 12 | I74: Credit Card | J74: N/A | K74: 45282 | L74: =IF(ISNUMBER(Table2[[#This Row],[Transaction Date]]),TEXT(Table2[[#This Row],[Transaction Date]],"mmmm"),"Unknown") -> December | M74: =IF(ISNUMBER(Table2[[#This Row],[Transaction Date]]),TEXT(Table2[[#This Row],[Transaction Date]],"dddd"),"Unknown") -> Friday | N74: =IF(OR(B74="",B74="unknown",B74="error",C74="",C74="unknown",C74="error",G74="",G74="error",G74="unknown"),1,0) -> 0 | O74: =IF(OR(C74="",C74="error",C74="unknown"),"Estimated","Actual") -> Actual
A75: TXN_8035512 | B75: Tea | C75: 3 | D75: =IF(OR(C75="",C75="UNKNOWN",C75="ERROR"),IFERROR(VALUE(G75)/VALUE(E75),""),VALUE(C75)) -> 3 | E75: =_xlfn.XLOOKUP(Table2[[#This Row],[Item]],Items_List!$A$2:$A$9,Items_List!$B$2:$B$9) -> 1.5 | F75: =IF(OR(E75="",E75="UNKNOWN",E75="ERROR"),_xlfn.XLOOKUP(Table2[[#This Row],[Item]],Items_List!A:A,Items_List!B:B),E75) -> 1.5 | G75: 4.5 | H75: =D75*F75 -> 4.5 | I75: Cash | J75: N/A | K75: 45228 | L75: =IF(ISNUMBER(Table2[[#This Row],[Transaction Date]]),TEXT(Table2[[#This Row],[Transaction Date]],"mmmm"),"Unknown") -> October | M75: =IF(ISNUMBER(Table2[[#This Row],[Transaction Date]]),TEXT(Table2[[#This Row],[Transaction Date]],"dddd"),"Unknown") -> Sunday | N75: =IF(OR(B75="",B75="unknown",B75="error",C75="",C75="unknown",C75="error",G75="",G75="error",G75="unknown"),1,0) -> 0 | O75: =IF(OR(C75="",C75="error",C75="unknown"),"Estimated","Actual") -> Actual
A76: TXN_8718498 | B76: Cake | C76: 5 | D76: =IF(OR(C76="",C76="UNKNOWN",C76="ERROR"),IFERROR(VALUE(G76)/VALUE(E76),""),VALUE(C76)) -> 5 | E76: 3 | F76: =IF(OR(E76="",E76="UNKNOWN",E76="ERROR"),_xlfn.XLOOKUP(Table2[[#This Row],[Item]],Items_List!A:A,Items_List!B:B),E76) -> 3 | G76: 15 | H76: =D76*F76 -> 15 | I76: Credit Card | J76: N/A | K76: 45046 | L76: =IF(ISNUMBER(Table2[[#This Row],[Transaction Date]]),TEXT(Table2[[#This Row],[Transaction Date]],"mmmm"),"Unknown") -> April | M76: =IF(ISNUMBER(Table2[[#This Row],[Transaction Date]]),TEXT(Table2[[#This Row],[Transaction Date]],"dddd"),"Unknown") -> Sunday | N76: =IF(OR(B76="",B76="unknown",B76="error",C76="",C76="unknown",C76="error",G76="",G76="error",G76="unknown"),1,0) -> 0 | O76: =IF(OR(C76="",C76="error",C76="unknown"),"Estimated","Actual") -> Actual
A77: TXN_3955361 | B77: Cookie | C77: 5 | D77: =IF(OR(C77="",C77="UNKNOWN",C77="ERROR"),IFERROR(VALUE(G77)/VALUE(E77),""),VALUE(C77)) -> 5 | E77: 1 | F77: =IF(OR(E77="",E77="UNKNOWN",E77="ERROR"),_xlfn.XLOOKUP(Table2[[#This Row],[Item]],Items_List!A:A,Items_List!B:B),E77) -> 1 | G77: 5 | H77: =D77*F77 -> 5 | I77: N/A | J77: Takeaway | K77: 45018 | L77: =IF(ISNUMBER(Table2[[#This Row],[Transaction Date]]),TEXT(Table2[[#This Row],[Transaction Date]],"mmmm"),"Unknown") -> April | M77: =IF(ISNUMBER(Table2[[#This Row],[Transaction Date]]),TEXT(Table2[[#This Row],[Transaction Date]],"dddd"),"Unknown") -> Sunday | N77: =IF(OR(B77="",B77="unknown",B77="error",C77="",C77="unknown",C77="error",G77="",G77="error",G77="unknown"),1,0) -> 0 | O77: =IF(OR(C77="",C77="error",C77="unknown"),"Estimated","Actual") -> Actual
A78: TXN_8976658 | B78: Tea | C78: 2 | D78: =IF(OR(C78="",C78="UNKNOWN",C78="ERROR"),IFERROR(VALUE(G78)/VALUE(E78),""),VALUE(C78)) -> 2 | E78: 1.5 | F78: =IF(OR(E78="",E78="UNKNOWN",E78="ERROR"),_xlfn.XLOOKUP(Table2[[#This Row],[Item]],Items_List!A:A,Items_List!B:B),E78) -> 1.5 | G78: 3 | H78: =D78*F78 -> 3 | I78: Credit Card | J78: In-store | K78: 45154 | L78: =IF(ISNUMBER(Table2[[#This Row],[Transaction Date]]),TEXT(Table2[[#This Row],[Transaction Date]],"mmmm"),"Unknown") -> August | M78: =IF(ISNUMBER(Table2[[#This Row],[Transaction Date]]),TEXT(Table2[[#This Row],[Transaction Date]],"dddd"),"Unknown") -> Wednesday | N78: =IF(OR(B78="",B78="unknown",B78="error",C78="",C78="unknown",C78="error",G78="",G78="error",G78="unknown"),1,0) -> 0 | O78: =IF(OR(C78="",C78="error",C78="unknown"),"Estimated","Actual") -> Actual
A79: TXN_2725602 | B79: Juice | C79: 5 | D79: =IF(OR(C79="",C79="UNKNOWN",C79="ERROR"),IFERROR(VALUE(G79)/VALUE(E79),""),VALUE(C79)) -> 5 | E79: 3 | F79: =IF(OR(E79="",E79="UNKNOWN",E79="ERROR"),_xlfn.XLOOKUP(Table2[[#This Row],[Item]],Items_List!A:A,Items_List!B:B),E79) -> 3 | G79: 15 | H79: =D79*F79 -> 15 | I79: Credit Card | J79: N/A | K79: 45179 | L79: =IF(ISNUMBER(Table2[[#This Row],[Transaction Date]]),TEXT(Table2[[#This Row],[Transaction Date]],"mmmm"),"Unknown") -> September | M79: =IF(ISNUMBER(Table2[[#This Row],[Transaction Date]]),TEXT(Table2[[#This Row],[Transaction Date]],"dddd"),"Unknown") -> Sunday | N79: =IF(OR(B79="",B79="unknown",B79="error",C79="",C79="unknown",C79="error",G79="",G79="error",G79="unknown"),1,0) -> 0 | O79: =IF(OR(C79="",C79="error",C79="unknown"),"Estimated","Actual") -> Actual
A80: TXN_3011323 | B80: Coffee | C80: 3 | D80: =IF(OR(C80="",C80="UNKNOWN",C80="ERROR"),IFERROR(VALUE(G80)/VALUE(E80),""),VALUE(C80)) -> 3 | E80: 2 | F80: =IF(OR(E80="",E80="UNKNOWN",E80="ERROR"),_xlfn.XLOOKUP(Table2[[#This Row],[Item]],Items_List!A:A,Items_List!B:B),E80) -> 2 | G80: 6 | H80: =D80*F80 -> 6 | I80: Credit Card | J80: N/A | K80: 44992 | L80: =IF(ISNUMBER(Table2[[#This Row],[Transaction Date]]),TEXT(Table2[[#This Row],[Transaction Date]],"mmmm"),"Unknown") -> March | M80: =IF(ISNUMBER(Table2[[#This Row],[Transaction Date]]),TEXT(Table2[[#This Row],[Transaction Date]],"dddd"),"Unknown") -> Tuesday | N80: =IF(OR(B80="",B80="unknown",B80="error",C80="",C80="unknown",C80="error",G80="",G80="error",G80="unknown"),1,0) -> 0 | O80: =IF(OR(C80="",C80="error",C80="unknown"),"Estimated","Actual") -> Actual
A81: TXN_6289610 | B81: Juice | C81: 3 | D81: =IF(OR(C81="",C81="UNKNOWN",C81="ERROR"),IFERROR(VALUE(G81)/VALUE(E81),""),VALUE(C81)) -> 3 | E81: 3 | F81: =IF(OR(E81="",E81="UNKNOWN",E81="ERROR"),_xlfn.XLOOKUP(Table2[[#This Row],[Item]],Items_List!A:A,Items_List!B:B),E81) -> 3 | G81: UNKNOWN | H81: =D81*F81 -> 9 | I81: Cash | J81: Takeaway | K81: 45145 | L81: =IF(ISNUMBER(Table2[[#This Row],[Transaction Date]]),TEXT(Table2[[#This Row],[Transaction Date]],"mmmm"),"Unknown") -> August | M81: =IF(ISNUMBER(Table2[[#This Row],[Transaction Date]]),TEXT(Table2[[#This Row],[Transaction Date]],"dddd"),"Unknown") -> Monday | N81: =IF(OR(B81="",B81="unknown",B81="error",C81="",C81="unknown",C81="error",G81="",G81="error",G81="unknown"),1,0) -> 1 | O81: =IF(OR(C81="",C81="error",C81="unknown"),"Estimated","Actual") -> Actual
A82: TXN_8268061 | B82: Salad | C82: 3 | D82: =IF(OR(C82="",C82="UNKNOWN",C82="ERROR"),IFERROR(VALUE(G82)/VALUE(E82),""),VALUE(C82)) -> 3 | E82: 5 | F82: =IF(OR(E82="",E82="UNKNOWN",E82="ERROR"),_xlfn.XLOOKUP(Table2[[#This Row],[Item]],Items_List!A:A,Items_List!B:B),E82) -> 5 | G82: 15 | H82: =D82*F82 -> 15 | I82: N/A | J82: Takeaway | K82: 45158 | L82: =IF(ISNUMBER(Table2[[#This Row],[Transaction Date]]),TEXT(Table2[[#This Row],[Transaction Date]],"mmmm"),"Unknown") -> August | M82: =IF(ISNUMBER(Table2[[#This Row],[Transaction Date]]),TEXT(Table2[[#This Row],[Transaction Date]],"dddd"),"Unknown") -> Sunday | N82: =IF(OR(B82="",B82="unknown",B82="error",C82="",C82="unknown",C82="error",G82="",G82="error",G82="unknown"),1,0) -> 0 | O82: =IF(OR(C82="",C82="error",C82="unknown"),"Estimated","Actual") -> Actual
A83: TXN_5220895 | B83: Salad | C83: 5 | D83: =IF(OR(C83="",C83="UNKNOWN",C83="ERROR"),IFERROR(VALUE(G83)/VALUE(E83),""),VALUE(C83)) -> 5 | E83: 5 | F83: =IF(OR(E83="",E83="UNKNOWN",E83="ERROR"),_xlfn.XLOOKUP(Table2[[#This Row],[Item]],Items_List!A:A,Items_List!B:B),E83) -> 5 | G83: 25 | H83: =D83*F83 -> 25 | I83: Cash | J83: In-store | K83: 45087 | L83: =IF(ISNUMBER(Table2[[#This Row],[Transaction Date]]),TEXT(Table2[[#This Row],[Transaction Date]],"mmmm"),"Unknown") -> June | M83: =IF(ISNUMBER(Table2[[#This Row],[Transaction Date]]),TEXT(Table2[[#This Row],[Transaction Date]],"dddd"),"Unknown") -> Saturday | N83: =IF(OR(B83="",B83="unknown",B83="error",C83="",C83="unknown",C83="error",G83="",G83="error",G83="unknown"),1,0) -> 0 | O83: =IF(OR(C83="",C83="error",C83="unknown"),"Estimated","Actual") -> Actual
A84: TXN_3085509 | B84: Coffee | C84: 4 | D84: =IF(OR(C84="",C84="UNKNOWN",C84="ERROR"),IFERROR(VALUE(G84)/VALUE(E84),""),VALUE(C84)) -> 4 | E84: 2 | F84: =IF(OR(E84="",E84="UNKNOWN",E84="ERROR"),_xlfn.XLOOKUP(Table2[[#This Row],[Item]],Items_List!A:A,Items_List!B:B),E84) -> 2 | G84: 8 | H84: =D84*F84 -> 8 | I84: Digital Wallet | J84: In-store | K84: 45031 | L84: =IF(ISNUMBER(Table2[[#This Row],[Transaction Date]]),TEXT(Table2[[#This Row],[Transaction Date]],"mmmm"),"Unknown") -> April | M84: =IF(ISNUMBER(Table2[[#This Row],[Transaction Date]]),TEXT(Table2[[#This Row],[Transaction Date]],"dddd"),"Unknown") -> Saturday | N84: =IF(OR(B84="",B84="unknown",B84="error",C84="",C84="unknown",C84="error",G84="",G84="error",G84="unknown"),1,0) -> 0 | O84: =IF(OR(C84="",C84="error",C84="unknown"),"Estimated","Actual") -> Actual
A85: TXN_9999113 | B85: Juice | C85: 4 | D85: =IF(OR(C85="",C85="UNKNOWN",C85="ERROR"),IFERROR(VALUE(G85)/VALUE(E85),""),VALUE(C85)) -> 4 | E85: 3 | F85: =IF(OR(E85="",E85="UNKNOWN",E85="ERROR"),_xlfn.XLOOKUP(Table2[[#This Row],[Item]],Items_List!A:A,Items_List!B:B),E85) -> 3 | G85: 12 | H85: =D85*F85 -> 12 | I85: Cash | J85: Takeaway | K85: 45073 | L85: =IF(ISNUMBER(Table2[[#This Row],[Transaction Date]]),TEXT(Table2[[#This Row],[Transaction Date]],"mmmm"),"Unknown") -> May | M85: =IF(ISNUMBER(Table2[[#This Row],[Transaction Date]]),TEXT(Table2[[#This Row],[Transaction Date]],"dddd"),"Unknown") -> Saturday | N85: =IF(OR(B85="",B85="unknown",B85="error",C85="",C85="unknown",C85="error",G85="",G85="error",G85="unknown"),1,0) -> 0 | O85: =IF(OR(C85="",C85="error",C85="unknown"),"Estimated","Actual") -> Actual
A86: TXN_8779771 | B86: Coffee | C86: 4 | D86: =IF(OR(C86="",C86="UNKNOWN",C86="ERROR"),IFERROR(VALUE(G86)/VALUE(E86),""),VALUE(C86)) -> 4 | E86: 2 | F86: =IF(OR(E86="",E86="UNKNOWN",E86="ERROR"),_xlfn.XLOOKUP(Table2[[#This Row],[Item]],Items_List!A:A,Items_List!B:B),E86) -> 2 | G86: 8 | H86: =D86*F86 -> 8 | I86: Cash | J86: In-store | K86: 45132 | L86: =IF(ISNUMBER(Table2[[#This Row],[Transaction Date]]),TEXT(Table2[[#This Row],[Transaction Date]],"mmmm"),"Unknown") -> July | M86: =IF(ISNUMBER(Table2[[#This Row],[Transaction Date]]),TEXT(Table2[[#This Row],[Transaction Date]],"dddd"),"Unknown") -> Tuesday | N86: =IF(OR(B86="",B86="unknown",B86="error",C86="",C86="unknown",C86="error",G86="",G86="error",G86="unknown"),1,0) -> 0 | O86: =IF(OR(C86="",C86="error",C86="unknown"),"Estimated","Actual") -> Actual
A87: TXN_1621920 | B87: Salad | C87: 3 | D87: =IF(OR(C87="",C87="UNKNOWN",C87="ERROR"),IFERROR(VALUE(G87)/VALUE(E87),""),VALUE(C87)) -> 3 | E87: 5 | F87: =IF(OR(E87="",E87="UNKNOWN",E87="ERROR"),_xlfn.XLOOKUP(Table2[[#This Row],[Item]],Items_List!A:A,Items_List!B:B),E87) -> 5 | G87: 15 | H87: =D87*F87 -> 15 | I87: N/A | J87: Takeaway | K87: 45227 | L87: =IF(ISNUMBER(Table2[[#This Row],[Transaction Date]]),TEXT(Table2[[#This Row],[Transaction Date]],"mmmm"),"Unknown") -> October | M87: =IF(ISNUMBER(Table2[[#This Row],[Transaction Date]]),TEXT(Table2[[#This Row],[Transaction Date]],"dddd"),"Unknown") -> Saturday | N87: =IF(OR(B87="",B87="unknown",B87="error",C87="",C87="unknown",C87="error",G87="",G87="error",G87="unknown"),1,0) -> 0 | O87: =IF(OR(C87="",C87="error",C87="unknown"),"Estimated","Actual") -> Actual
A88: TXN_3808639 | B88: Juice | C88: 2 | D88: =IF(OR(C88="",C88="UNKNOWN",C88="ERROR"),IFERROR(VALUE(G88)/VALUE(E88),""),VALUE(C88)) -> 2 | E88: 3 | F88: =IF(OR(E88="",E88="UNKNOWN",E88="ERROR"),_xlfn.XLOOKUP(Table2[[#This Row],[Item]],Items_List!A:A,Items_List!B:B),E88) -> 3 | G88: 6 | H88: =D88*F88 -> 6 | I88: Digital Wallet | J88: Takeaway | K88: 45275 | L88: =IF(ISNUMBER(Table2[[#This Row],[Transaction Date]]),TEXT(Table2[[#This Row],[Transaction Date]],"mmmm"),"Unknown") -> December | M88: =IF(ISNUMBER(Table2[[#This Row],[Transaction Date]]),TEXT(Table2[[#This Row],[Transaction Date]],"dddd"),"Unknown") -> Friday | N88: =IF(OR(B88="",B88="unknown",B88="error",C88="",C88="unknown",C88="error",G88="",G88="error",G88="unknown"),1,0) -> 0 | O88: =IF(OR(C88="",C88="error",C88="unknown"),"Estimated","Actual") -> Actual
A89: TXN_7028009 | B89: Cake | C89: 4 | D89: =IF(OR(C89="",C89="UNKNOWN",C89="ERROR"),IFERROR(VALUE(G89)/VALUE(E89),""),VALUE(C89)) -> 4 | E89: 3 | F89: =IF(OR(E89="",E89="UNKNOWN",E89="ERROR"),_xlfn.XLOOKUP(Table2[[#This Row],[Item]],Items_List!A:A,Items_List!B:B),E89) -> 3 | G89: 12 | H89: =D89*F89 -> 12 | I89: N/A | J89: Takeaway | L89: =IF(ISNUMBER(Table2[[#This Row],[Transaction Date]]),TEXT(Table2[[#This Row],[Transaction Date]],"mmmm"),"Unknown") -> Unknown | M89: =IF(ISNUMBER(Table2[[#This Row],[Transaction Date]]),TEXT(Table2[[#This Row],[Transaction Date]],"dddd"),"Unknown") -> Unknown | N89: =IF(OR(B89="",B89="unknown",B89="error",C89="",C89="unknown",C89="error",G89="",G89="error",G89="unknown"),1,0) -> 0 | O89: =IF(OR(C89="",C89="error",C89="unknown"),"Estimated","Actual") -> Actual
A90: TXN_7447872 | B90: Juice | C90: 2 | D90: =IF(OR(C90="",C90="UNKNOWN",C90="ERROR"),IFERROR(VALUE(G90)/VALUE(E90),""),VALUE(C90)) -> 2 | E90: =_xlfn.XLOOKUP(Table2[[#This Row],[Item]],Items_List!$A$2:$A$9,Items_List!$B$2:$B$9) -> 3 | F90: =IF(OR(E90="",E90="UNKNOWN",E90="ERROR"),_xlfn.XLOOKUP(Table2[[#This Row],[Item]],Items_List!A:A,Items_List!B:B),E90) -> 3 | G90: 6 | H90: =D90*F90 -> 6 | I90: N/A | J90: N/A | L90: =IF(ISNUMBER(Table2[[#This Row],[Transaction Date]]),TEXT(Table2[[#This Row],[Transaction Date]],"mmmm"),"Unknown") -> Unknown | M90: =IF(ISNUMBER(Table2[[#This Row],[Transaction Date]]),TEXT(Table2[[#This Row],[Transaction Date]],"dddd"),"Unknown") -> Unknown | N90: =IF(OR(B90="",B90="unknown",B90="error",C90="",C90="unknown",C90="error",G90="",G90="error",G90="unknown"),1,0) -> 0 | O90: =IF(OR(C90="",C90="error",C90="unknown"),"Estimated","Actual") -> Actual
A91: TXN_6955416 | B91: Salad | C91: 4 | D91: =IF(OR(C91="",C91="UNKNOWN",C91="ERROR"),IFERROR(VALUE(G91)/VALUE(E91),""),VALUE(C91)) -> 4 | E91: 5 | F91: =IF(OR(E91="",E91="UNKNOWN",E91="ERROR"),_xlfn.XLOOKUP(Table2[[#This Row],[Item]],Items_List!A:A,Items_List!B:B),E91) -> 5 | G91: 20 | H91: =D91*F91 -> 20 | I91: N/A | J91: In-store | K91: 44982 | L91: =IF(ISNUMBER(Table2[[#This Row],[Transaction Date]]),TEXT(Table2[[#This Row],[Transaction Date]],"mmmm"),"Unknown") -> February | M91: =IF(ISNUMBER(Table2[[#This Row],[Transaction Date]]),TEXT(Table2[[#This Row],[Transaction Date]],"dddd"),"Unknown") -> Saturday | N91: =IF(OR(B91="",B91="unknown",B91="error",C91="",C91="unknown",C91="error",G91="",G91="error",G91="unknown"),1,0) -> 0 | O91: =IF(OR(C91="",C91="error",C91="unknown"),"Estimated","Actual") -> Actual
A92: TXN_3775339 | B92: Cookie | C92: 3 | D92: =IF(OR(C92="",C92="UNKNOWN",C92="ERROR"),IFERROR(VALUE(G92)/VALUE(E92),""),VALUE(C92)) -> 3 | E92: 1 | F92: =IF(OR(E92="",E92="UNKNOWN",E92="ERROR"),_xlfn.XLOOKUP(Table2[[#This Row],[Item]],Items_List!A:A,Items_List!B:B),E92) -> 1 | G92: 3 | H92: =D92*F92 -> 3 | I92: Credit Card | J92: N/A | K92: 45019 | L92: =IF(ISNUMBER(Table2[[#This Row],[Transaction Date]]),TEXT(Table2[[#This Row],[Transaction Date]],"mmmm"),"Unknown") -> April | M92: =IF(ISNUMBER(Table2[[#This Row],[Transaction Date]]),TEXT(Table2[[#This Row],[Transaction Date]],"dddd"),"Unknown") -> Monday | N92: =IF(OR(B92="",B92="unknown",B92="error",C92="",C92="unknown",C92="error",G92="",G92="error",G92="unknown"),1,0) -> 0 | O92: =IF(OR(C92="",C92="error",C92="unknown"),"Estimated","Actual") -> Actual
A93: TXN_9547091 | B93: Cookie | C93: 3 | D93: =IF(OR(C93="",C93="UNKNOWN",C93="ERROR"),IFERROR(VALUE(G93)/VALUE(E93),""),VALUE(C93)) -> 3 | E93: 1 | F93: =IF(OR(E93="",E93="UNKNOWN",E93="ERROR"),_xlfn.XLOOKUP(Table2[[#This Row],[Item]],Items_List!A:A,Items_List!B:B),E93) -> 1 | G93: 3 | H93: =D93*F93 -> 3 | I93: Credit Card | J93: N/A | K93: 45207 | L93: =IF(ISNUMBER(Table2[[#This Row],[Transaction Date]]),TEXT(Table2[[#This Row],[Transaction Date]],"mmmm"),"Unknown") -> October | M93: =IF(ISNUMBER(Table2[[#This Row],[Transaction Date]]),TEXT(Table2[[#This Row],[Transaction Date]],"dddd"),"Unknown") -> Sunday | N93: =IF(OR(B93="",B93="unknown",B93="error",C93="",C93="unknown",C93="error",G93="",G93="error",G93="unknown"),1,0) -> 0 | O93: =IF(OR(C93="",C93="error",C93="unknown"),"Estimated","Actual") -> Actual
A94: TXN_4358673 | B94: Cookie | C94: 5 | D94: =IF(OR(C94="",C94="UNKNOWN",C94="ERROR"),IFERROR(VALUE(G94)/VALUE(E94),""),VALUE(C94)) -> 5 | E94: 1 | F94: =IF(OR(E94="",E94="UNKNOWN",E94="ERROR"),_xlfn.XLOOKUP(Table2[[#This Row],[Item]],Items_List!A:A,Items_List!B:B),E94) -> 1 | G94: 5 | H94: =D94*F94 -> 5 | I94: Digital Wallet | J94: Takeaway | K94: 45288 | L94: =IF(ISNUMBER(Table2[[#This Row],[Transaction Date]]),TEXT(Table2[[#This Row],[Transaction Date]],"mmmm"),"Unknown") -> December | M94: =IF(ISNUMBER(Table2[[#This Row],[Transaction Date]]),TEXT(Table2[[#This Row],[Transaction Date]],"dddd"),"Unknown") -> Thursday | N94: =IF(OR(B94="",B94="unknown",B94="error",C94="",C94="unknown",C94="error",G94="",G94="error",G94="unknown"),1,0) -> 0 | O94: =IF(OR(C94="",C94="error",C94="unknown"),"Estimated","Actual") -> Actual
A95: TXN_4174591 | B95: Tea | C95: 4 | D95: =IF(OR(C95="",C95="UNKNOWN",C95="ERROR"),IFERROR(VALUE(G95)/VALUE(E95),""),VALUE(C95)) -> 4 | E95: 1.5 | F95: =IF(OR(E95="",E95="UNKNOWN",E95="ERROR"),_xlfn.XLOOKUP(Table2[[#This Row],[Item]],Items_List!A:A,Items_List!B:B),E95) -> 1.5 | G95: 6 | H95: =D95*F95 -> 6 | I95: Digital Wallet | J95: N/A | K95: 45168 | L95: =IF(ISNUMBER(Table2[[#This Row],[Transaction Date]]),TEXT(Table2[[#This Row],[Transaction Date]],"mmmm"),"Unknown") -> August | M95: =IF(ISNUMBER(Table2[[#This Row],[Transaction Date]]),TEXT(Table2[[#This Row],[Transaction Date]],"dddd"),"Unknown") -> Wednesday | N95: =IF(OR(B95="",B95="unknown",B95="error",C95="",C95="unknown",C95="error",G95="",G95="error",G95="unknown"),1,0) -> 0 | O95: =IF(OR(C95="",C95="error",C95="unknown"),"Estimated","Actual") -> Actual
A96: TXN_3398520 | B96: Sandwich | C96: 1 | D96: =IF(OR(C96="",C96="UNKNOWN",C96="ERROR"),IFERROR(VALUE(G96)/VALUE(E96),""),VALUE(C96)) -> 1 | E96: 4 | F96: =IF(OR(E96="",E96="UNKNOWN",E96="ERROR"),_xlfn.XLOOKUP(Table2[[#This Row],[Item]],Items_List!A:A,Items_List!B:B),E96) -> 4 | G96: 4 | H96: =D96*F96 -> 4 | I96: N/A | J96: In-store | K96: 44960 | L96: =IF(ISNUMBER(Table2[[#This Row],[Transaction Date]]),TEXT(Table2[[#This Row],[Transaction Date]],"mmmm"),"Unknown") -> February | M96: =IF(ISNUMBER(Table2[[#This Row],[Transaction Date]]),TEXT(Table2[[#This Row],[Transaction Date]],"dddd"),"Unknown") -> Friday | N96: =IF(OR(B96="",B96="unknown",B96="error",C96="",C96="unknown",C96="error",G96="",G96="error",G96="unknown"),1,0) -> 0 | O96: =IF(OR(C96="",C96="error",C96="unknown"),"Estimated","Actual") -> Actual
A97: TXN_6171384 | B97: Smoothie | C97: 2 | D97: =IF(OR(C97="",C97="UNKNOWN",C97="ERROR"),IFERROR(VALUE(G97)/VALUE(E97),""),VALUE(C97)) -> 2 | E97: 4 | F97: =IF(OR(E97="",E97="UNKNOWN",E97="ERROR"),_xlfn.XLOOKUP(Table2[[#This Row],[Item]],Items_List!A:A,Items_List!B:B),E97) -> 4 | G97: 8 | H97: =D97*F97 -> 8 | I97: Credit Card | J97: N/A | K97: 45181 | L97: =IF(ISNUMBER(Table2[[#This Row],[Transaction Date]]),TEXT(Table2[[#This Row],[Transaction Date]],"mmmm"),"Unknown") -> September | M97: =IF(ISNUMBER(Table2[[#This Row],[Transaction Date]]),TEXT(Table2[[#This Row],[Transaction Date]],"dddd"),"Unknown") -> Tuesday | N97: =IF(OR(B97="",B97="unknown",B97="error",C97="",C97="unknown",C97="error",G97="",G97="error",G97="unknown"),1,0) -> 0 | O97: =IF(OR(C97="",C97="error",C97="unknown"),"Estimated","Actual") -> Actual
A98: TXN_2530938 | B98: Smoothie | C98: 5 | D98: =IF(OR(C98="",C98="UNKNOWN",C98="ERROR"),IFERROR(VALUE(G98)/VALUE(E98),""),VALUE(C98)) -> 5 | E98: 4 | F98: =IF(OR(E98="",E98="UNKNOWN",E98="ERROR"),_xlfn.XLOOKUP(Table2[[#This Row],[Item]],Items_List!A:A,Items_List!B:B),E98) -> 4 | G98: 20 | H98: =D98*F98 -> 20 | I98: N/A | J98: Takeaway | K98: 45043 | L98: =IF(ISNUMBER(Table2[[#This Row],[Transaction Date]]),TEXT(Table2[[#This Row],[Transaction Date]],"mmmm"),"Unknown") -> April | M98: =IF(ISNUMBER(Table2[[#This Row],[Transaction Date]]),TEXT(Table2[[#This Row],[Transaction Date]],"dddd"),"Unknown") -> Thursday | N98: =IF(OR(B98="",B98="unknown",B98="error",C98="",C98="unknown",C98="error",G98="",G98="error",G98="unknown"),1,0) -> 0 | O98: =IF(OR(C98="",C98="error",C98="unknown"),"Estimated","Actual") -> Actual
A99: TXN_3314971 | B99: Juice | C99: 3 | D99: =IF(OR(C99="",C99="UNKNOWN",C99="ERROR"),IFERROR(VALUE(G99)/VALUE(E99),""),VALUE(C99)) -> 3 | E99: 3 | F99: =IF(OR(E99="",E99="UNKNOWN",E99="ERROR"),_xlfn.XLOOKUP(Table2[[#This Row],[Item]],Items_List!A:A,Items_List!B:B),E99) -> 3 | G99: 9 | H99: =D99*F99 -> 9 | I99: Digital Wallet | J99: N/A | K99: 45050 | L99: =IF(ISNUMBER(Table2[[#This Row],[Transaction Date]]),TEXT(Table2[[#This Row],[Transaction Date]],"mmmm"),"Unknown") -> May | M99: =IF(ISNUMBER(Table2[[#This Row],[Transaction Date]]),TEXT(Table2[[#This Row],[Transaction Date]],"dddd"),"Unknown") -> Thursday | N99: =IF(OR(B99="",B99="unknown",B99="error",C99="",C99="unknown",C99="error",G99="",G99="error",G99="unknown"),1,0) -> 0 | O99: =IF(OR(C99="",C99="error",C99="unknown"),"Estimated","Actual") -> Actual
A100: TXN_3092382 | B100: Coffee | C100: 5 | D100: =IF(OR(C100="",C100="UNKNOWN",C100="ERROR"),IFERROR(VALUE(G100)/VALUE(E100),""),VALUE(C100)) -> 5 | E100: 2 | F100: =IF(OR(E100="",E100="UNKNOWN",E100="ERROR"),_xlfn.XLOOKUP(Table2[[#This Row],[Item]],Items_List!A:A,Items_List!B:B),E100) -> 2 | G100: 10 | H100: =D100*F100 -> 10 | I100: Digital Wallet | J100: N/A | K100: 44978 | L100: =IF(ISNUMBER(Table2[[#This Row],[Transaction Date]]),TEXT(Table2[[#This Row],[Transaction Date]],"mmmm"),"Unknown") -> February | M100: =IF(ISNUMBER(Table2[[#This Row],[Transaction Date]]),TEXT(Table2[[#This Row],[Transaction Date]],"dddd"),"Unknown") -> Tuesday | N100: =IF(OR(B100="",B100="unknown",B100="error",C100="",C100="unknown",C100="error",G100="",G100="error",G100="unknown"),1,0) -> 0 | O100: =IF(OR(C100="",C100="error",C100="unknown"),"Estimated","Actual") -> Actual
...

Sheet Items_List
A1: Item | B1: Price
A2: Coffee | B2: 2
A3: Cake | B3: 3
A4: Salad | B4: 5
A5: Cookie | B5: 1
A6: Smoothie | B6: 4
A7: Sandwich | B7: 4
A8: Juice | B8: 3
A9: Tea | B9: 1.5

Sheet dirty_cafe_sales
A1: Transaction ID | B1: Item | C1: Quantity | D1: Price Per Unit | E1: Total Spent | F1: Payment Method | G1: Location | H1: Transaction Date
A2: TXN_1961373 | B2: Coffee | C2: 2 | D2: 2 | E2: 4 | F2: Credit Card | G2: Takeaway | H2: 45177
A3: TXN_4977031 | B3: Cake | C3: 4 | D3: 3 | E3: 12 | F3: Cash | G3: In-store | H3: 45062
A4: TXN_4271903 | B4: Cookie | C4: 4 | D4: 1 | E4: ERROR | F4: Credit Card | G4: In-store | H4: 45126
A5: TXN_7034554 | B5: Salad | C5: 2 | D5: 5 | E5: 10 | F5: UNKNOWN | G5: UNKNOWN | H5: 45043
A6: TXN_3160411 | B6: Coffee | C6: 2 | D6: 2 | E6: 4 | F6: Digital Wallet | G6: In-store | H6: 45088
A7: TXN_2602893 | B7: Smoothie | C7: 5 | D7: 4 | E7: 20 | F7: Credit Card | H7: 45016
A8: TXN_4433211 | B8: UNKNOWN | C8: 3 | D8: 3 | E8: 9 | F8: ERROR | G8: Takeaway | H8: 45205
A9: TXN_6699534 | B9: Sandwich | C9: 4 | D9: 4 | E9: 16 | F9: Cash | G9: UNKNOWN | H9: 45227
A10: TXN_4717867 | C10: 5 | D10: 3 | E10: 15 | G10: Takeaway | H10: 45135
A11: TXN_2064365 | B11: Sandwich | C11: 5 | D11: 4 | E11: 20 | G11: In-store | H11: 45291
A12: TXN_2548360 | B12: Salad | C12: 5 | D12: 5 | E12: 25 | F12: Cash | G12: Takeaway | H12: 45237
A13: TXN_3051279 | B13: Sandwich | C13: 2 | D13: 4 | E13: 8 | F13: Credit Card | G13: Takeaway | H13: ERROR
A14: TXN_7619095 | B14: Sandwich | C14: 2 | D14: 4 | E14: 8 | F14: Cash | G14: In-store | H14: 45049
A15: TXN_9437049 | B15: Cookie | C15: 5 | D15: 1 | E15: 5 | G15: Takeaway | H15: 45078
A16: TXN_8915701 | B16: ERROR | C16: 2 | D16: 1.5 | E16: 3 | G16: In-store | H16: 45006
A17: TXN_2847255 | B17: Salad | C17: 3 | D17: 5 | E17: 15 | F17: Credit Card | G17: In-store | H17: 45245
A18: TXN_3765707 | B18: Sandwich | C18: 1 | D18: 4 | E18: 4 | H18: 45087
A19: TXN_6769710 | B19: Juice | C19: 2 | D19: 3 | E19: 6 | F19: Cash | G19: In-store | H19: 44981
A20: TXN_8876618 | B20: Cake | C20: 5 | D20: 3 | E20: 15 | F20: Cash | G20: ERROR | H20: 45010
A21: TXN_3709394 | B21: Juice | C21: 4 | D21: 3 | E21: 12 | F21: Cash | G21: Takeaway | H21: 44941
A22: TXN_3522028 | B22: Smoothie | C22: ERROR | D22: 4 | E22: 20 | F22: Cash | G22: In-store | H22: 45020
A23: TXN_3567645 | B23: Smoothie | C23: 4 | D23: 4 | E23: 16 | F23: Credit Card | G23: Takeaway | H23: 45015
A24: TXN_5132361 | B24: Sandwich | C24: 3 | D24: 4 | E24: 12 | F24: Digital Wallet | G24: Takeaway | H24: 45261
A25: TXN_2616390 | B25: Sandwich | C25: 2 | D25: 4 | E25: 8 | H25: 45187
A26: TXN_9400181 | B26: Sandwich | C26: 5 | D26: 4 | E26: 20 | F26: Cash | G26: In-store | H26: 45080
A27: TXN_7958992 | B27: Smoothie | C27: 3 | D27: 4 | F27: UNKNOWN | G27: UNKNOWN | H27: 45273
A28: TXN_5183041 | B28: Cookie | C28: 5 | D28: 1 | E28: 5 | F28: Credit Card | G28: In-store | H28: 45036
A29: TXN_5695074 | B29: Juice | C29: 4 | D29: 3 | E29: 12 | F29: Credit Card | G29: Takeaway | H29: 45026
A30: TXN_8467949 | B30: Smoothie | C30: 5 | D30: 4 | E30: 20 | F30: Credit Card | H30: 44996
A31: TXN_7640952 | B31: Cake | C31: 4 | D31: 3 | E31: 12 | F31: Digital Wallet | G31: Takeaway | H31: ERROR
A32: TXN_1736287 | C32: 5 | D32: 2 | E32: 10 | F32: Digital Wallet | H32: 45079
A33: TXN_8927252 | B33: UNKNOWN | C33: 2 | D33: 1 | E33: ERROR | F33: Credit Card | G33: ERROR | H33: 45236
A34: TXN_9677376 | B34: Smoothie | C34: 4 | D34: 4 | E34: 16 | G34: In-store | H34: 45153
A35: TXN_7710508 | B35: UNKNOWN | C35: 5 | D35: 1 | E35: 5 | F35: Cash | H35: ERROR
A36: TXN_8853997 | B36: Smoothie | C36: 2 | D36: 4 | E36: 8 | F36: Digital Wallet | G36: Takeaway | H36: 45208
A37: TXN_9130559 | B37: Sandwich | C37: 1 | D37: 4 | E37: 4 | F37: Credit Card | G37: UNKNOWN | H37: 45074
A38: TXN_6855453 | B38: UNKNOWN | C38: 4 | D38: 3 | E38: 12 | G38: In-store | H38: 45124
A39: TXN_1080432 | B39: Salad | C39: 2 | D39: 5 | E39: 10 | F39: Credit Card | G39: In-store | H39: 45045
A40: TXN_2655815 | B40: Smoothie | C40: 4 | D40: 4 | E40: 16 | G40: Takeaway | H40: 45085
A41: TXN_6688524 | B41: Coffee | C41: 4 | D41: 2 | E41: 8 | F41: ERROR | H41: 45106
A42: TXN_2083138 | B42: Smoothie | C42: 3 | D42: 4 | E42: 12 | G42: In-store | H42: 45033
A43: TXN_2427584 | B43: Sandwich | C43: 4 | D43: 4 | E43: 16 | G43: Takeaway | H43: 45282
A44: TXN_6650263 | B44: Tea | C44: 2 | D44: 1.5 | E44: UNKNOWN | G44: Takeaway | H44: 44936
A45: TXN_9620080 | B45: Juice | C45: 4 | D45: 3 | E45: 12 | G45: Takeaway | H45: 45201
A46: TXN_1491578 | B46: Cookie | C46: 2 | D46: 1 | E46: 2 | H46: 44980
A47: TXN_5455792 | B47: Salad | C47: 3 | D47: 5 | E47: 15 | F47: Cash | H47: 45007
A48: TXN_8078640 | B48: Juice | C48: 4 | D48: 3 | E48: 12 | F48: Digital Wallet | G48: In-store | H48: 45233
A49: TXN_9499313 | B49: Juice | C49: 5 | D49: 3 | E49: 15 | H49: 44987
A50: TXN_8201146 | B50: Juice | C50: 5 | D50: 3 | E50: 15 | F50: Cash | H50: 45103
A51: TXN_8230936 | B51: Cake | C51: 3 | D51: 3 | E51: 9 | G51: ERROR | H51: 45048
A52: TXN_7742742 | B52: Cake | C52: 5 | D52: 3 | E52: 15 | G52: Takeaway | H52: 45174
A53: TXN_6342161 | B53: Salad | C53: 5 | D53: 5 | E53: 25 | F53: ERROR | G53: Takeaway | H53: 44934
A54: TXN_8914892 | B54: UNKNOWN | C54: 5 | D54: 5 | E54: 25 | F54: Digital Wallet | H54: 45000
A55: TXN_3363746 | B55: Smoothie | C55: 3 | D55: 4 | E55: 12 | F55: Credit Card | H55: 45255
A56: TXN_8614868 | B56: Smoothie | C56: 5 | D56: 4 | E56: 20 | F56: Digital Wallet | G56: Takeaway | H56: 45265
A57: TXN_5522862 | B57: Cookie | C57: ERROR | D57: 1 | E57: 2 | F57: Credit Card | G57: Takeaway | H57: 45004
A58: TXN_3578141 | B58: Cake | C58: 5 | E58: 15 | G58: Takeaway | H58: 45104
A59: TXN_2080895 | B59: Cake | C59: UNKNOWN | D59: 3 | E59: 3 | F59: Digital Wallet | G59: In-store | H59: 45035
A60: TXN_6421134 | B60: Sandwich | C60: 4 | D60: 4 | E60: 16 | F60: Cash | G60: Takeaway | H60: 45233
A61: TXN_8813311 | B61: Juice | C61: 5 | D61: 3 | E61: 15 | G61: In-store | H61: 45206
A62: TXN_9023317 | B62: Salad | C62: 1 | D62: 5 | E62: 5 | H62: 45199
A63: TXN_8051289 | C63: 1 | D63: 3 | E63: 3 | G63: In-store | H63: 45208
A64: TXN_2537617 | B64: Sandwich | C64: 1 | D64: 4 | E64: 4 | F64: Cash | H64: 45073
A65: TXN_9099694 | B65: UNKNOWN | C65: 3 | D65: 5 | E65: 15 | G65: Takeaway | H65: 45248
A66: TXN_9230615 | B66: Smoothie | C66: 4 | D66: 4 | E66: 16 | F66: Digital Wallet | H66: 45078
A67: TXN_4987129 | B67: Sandwich | C67: 3 | G67: In-store | H67: 45219
A68: TXN_8501819 | B68: Juice | D68: 3 | E68: 6 | F68: Cash | H68: 45015
A69: TXN_3068204 | B69: Cookie | C69: 1 | D69: 1 | E69: 1 | F69: Credit Card | G69: Takeaway | H69: 45202
A70: TXN_8427104 | B70: Salad | C70: 2 | D70: ERROR | E70: 10 | G70: In-store | H70: 45226
A71: TXN_8471743 | B71: ERROR | C71: 5 | D71: 3 | E71: 15 | F71: Digital Wallet | G71: In-store | H71: 45022
A72: TXN_2621580 | B72: Tea | C72: 2 | D72: 1.5 | E72: 3 | F72: Cash | G72: In-store | H72: 45007
A73: TXN_4726376 | B73: Cake | C73: 2 | D73: 3 | E73: 6 | F73: Credit Card | G73: In-store | H73: 44957
A74: TXN_6044979 | C74: 1 | D74: 1 | E74: 1 | F74: Cash | G74: In-store | H74: 45268
A75: TXN_4238417 | B75: Salad | C75: 2 | D75: 5 | E75: 10 | G75: ERROR | H75: 45096
A76: TXN_1900620 | B76: Smoothie | C76: 2 | D76: 4 | E76: 8 | F76: Credit Card | G76: ERROR | H76: 45274
A77: TXN_6420335 | B77: Coffee | C77: 1 | D77: 2 | E77: 2 | F77: Cash | G77: Takeaway | H77: 45123
A78: TXN_3858209 | B78: Sandwich | C78: 4 | D78: 4 | E78: 16 | F78: Cash | H78: 44979
A79: TXN_2091733 | B79: Salad | C79: 1 | D79: 5 | E79: 5 | G79: In-store
A80: TXN_8735480 | B80: Tea | C80: 5 | D80: 1.5 | E80: 7.5 | F80: Cash | H80: 45079
A81: TXN_3829165 | B81: Juice | C81: 4 | D81: 3 | E81: 12 | F81: Cash | G81: In-store | H81: 45092
A82: TXN_3748616 | B82: Coffee | C82: 2 | D82: 2 | E82: 4 | F82: Credit Card | G82: In-store | H82: 45269
A83: TXN_1993289 | B83: Sandwich | C83: 2 | D83: 4 | E83: 8 | G83: In-store | H83: 45034
A84: TXN_2123367 | B84: Cookie | C84: 2 | D84: 1 | E84: 2 | H84: 45237
A85: TXN_5266394 | B85: Cake | C85: 3 | D85: 3 | E85: 9 | F85: Cash | G85: In-store | H85: 45227
A86: TXN_5107946 | B86: Cake | C86: 4 | D86: 3 | E86: 12 | F86: Credit Card | H86: 45282
A87: TXN_8035512 | B87: Tea | C87: 3 | E87: 4.5 | F87: Cash | G87: UNKNOWN | H87: 45228
A88: TXN_8718498 | B88: Cake | C88: 5 | D88: 3 | E88: 15 | F88: Credit Card | G88: ERROR | H88: 45046
A89: TXN_3955361 | B89: Cookie | C89: 5 | D89: 1 | E89: 5 | G89: Takeaway | H89: 45018
A90: TXN_9487821 | B90: ERROR | C90: 1 | D90: 5 | E90: 5 | F90: Digital Wallet | G90: Takeaway | H90: 45070
A91: TXN_4132730 | C91: 5 | D91: 1 | E91: 5 | G91: In-store | H91: 44997
A92: TXN_8976658 | B92: Tea | C92: 2 | D92: 1.5 | E92: 3 | F92: Credit Card | G92: In-store | H92: 45154
A93: TXN_5455936 | B93: UNKNOWN | C93: 5 | D93: 3 | E93: 15 | G93: In-store | H93: 45227
A94: TXN_2725602 | B94: Juice | C94: 5 | D94: 3 | E94: 15 | F94: Credit Card | H94: 45179
A95: TXN_3011323 | B95: Coffee | C95: 3 | D95: 2 | E95: 6 | F95: Credit Card | H95: 44992
A96: TXN_6289610 | B96: Juice | C96: 3 | D96: 3 | E96: UNKNOWN | F96: Cash | G96: Takeaway | H96: 45145
A97: TXN_8268061 | B97: Salad | C97: 3 | D97: 5 | E97: 15 | F97: ERROR | G97: Takeaway | H97: 45158
A98: TXN_5220895 | B98: Salad | C98: 5 | D98: 5 | E98: 25 | F98: Cash | G98: In-store | H98: 45087
A99: TXN_3085509 | B99: Coffee | C99: 4 | D99: 2 | E99: 8 | F99: Digital Wallet | G99: In-store | H99: 45031
A100: TXN_9999113 | B100: Juice | C100: 4 | D100: 3 | E100: 12 | F100: Cash | G100: Takeaway | H100: 45073
...
